// converted by version 1.3
// on Thu Feb 05 12:27:47 CET 2015

.package com/orange/tim {
	.aid 0x1:0x2:0x3:0x4:0x5:0x6:0x7:0x8:0x9;
	.version 2.63;

	.imports {
		0xA0:0x0:0x0:0x0:0x62:0x0:0x1 1.0;		//java/lang
		0xA0:0x0:0x0:0x0:0x62:0x1:0x1 1.2;		//javacard/framework
		0xA0:0x0:0x0:0x0:0x62:0x1:0x2 1.2;		//javacard/security
		0xA0:0x0:0x0:0x0:0x62:0x2:0x1 1.2;		//javacardx/crypto
	}

	.applet {
		0x1:0x2:0x3:0x4:0x5:0x6:0x7:0x8:0x9:0x0:0x0 Tim;
	}

	.constantPool {
		// 0
		instanceFieldRef byte[] RequestTokenRW/tr_buffer;
		// 1
		instanceFieldRef byte Tim/TIM_SIM_VERSION;
		// 2
		instanceFieldRef short Tim/found_data_length;
		// 3
		instanceFieldRef short Tim/found_tokenKeyData_length;
		// 4
		instanceFieldRef short Tim/tokenKeyDataLength;
		// 5
		instanceFieldRef short Tim/requestDataLength;
		// 6
		instanceFieldRef short Tim/requestObjectLength;
		// 7
		instanceFieldRef short Tim/signedRequestObjectLength;
		// 8
		instanceFieldRef short Tim/jweDataLength;
		// 9
		instanceFieldRef short Tim/pubKeyLen;
		// 10
		instanceFieldRef short Tim/privKeyLen;
		// 11
		instanceFieldRef short Tim/timTokenLen;
		// 12
		instanceFieldRef short Tim/timTokenSignLen;
		// 13
		instanceFieldRef short Tim/dataToSignLength;
		// 14
		instanceFieldRef short Tim/signedDataLength;
		// 15
		instanceFieldRef byte[] Tim/tempBuf64;
		// 16
		instanceFieldRef byte[] Tim/rs256Header;
		// 17
		instanceFieldRef byte[] Tim/rs256HeaderB64;
		// 18
		instanceFieldRef byte[] Tim/sha1withrsaHeaderB64;
		// 19
		instanceFieldRef byte[] Tim/sha256Id;
		// 20
		instanceFieldRef short Tim/signRO_offset;
		// 21
		instanceFieldRef short Tim/signature_len;
		// 22
		instanceFieldRef short Tim/encryptRO_offset;
		// 23
		instanceFieldRef short Tim/encryptRO_length;
		// 24
		instanceFieldRef short Tim/encryptRO_encrypt_length;
		// 25
		instanceFieldRef byte[] Tim/cek;
		// 26
		instanceFieldRef byte[] Tim/iv_key;
		// 27
		instanceFieldRef byte[] Tim/cryptoErrorK;
		// 28
		instanceFieldRef byte[] Tim/cryptoErrorI;
		// 29
		instanceFieldRef byte[] Tim/cryptoErrorU;
		// 30
		instanceFieldRef byte[] Tim/cryptoErrorV;
		// 31
		instanceFieldRef byte[] Tim/cryptoErrorD;
		// 32
		instanceFieldRef boolean Tim/timeSet;
		// 33
		instanceFieldRef byte[] Tim/currentTime;
		// 34
		instanceFieldRef byte[] Tim/tempData;
		// 35
		instanceFieldRef short Tim/incomming;
		// 36
		instanceFieldRef short Tim/received_data_length;
		// 37
		instanceFieldRef short Tim/sent;
		// 38
		instanceFieldRef byte Tim/seq;
		// 39
		instanceFieldRef byte[] Tim/requestData;
		// 40
		instanceFieldRef byte[] Tim/requestObjectData;
		// 41
		instanceFieldRef byte[] Tim/encoded64;
		// 42
		instanceFieldRef byte[] Tim/encryptData;
		// 43
		instanceFieldRef byte[] Tim/requestObjectDataSignature;
		// 44
		instanceFieldRef byte[] Tim/signedRequestObjectData;
		// 45
		instanceFieldRef byte[] Tim/jweData;
		// 46
		instanceFieldRef byte[] Tim/pubKey;
		// 47
		instanceFieldRef byte[] Tim/privKey;
		// 48
		instanceFieldRef byte[] Tim/timToken;
		// 49
		instanceFieldRef byte[] Tim/timTokenSignature;
		// 50
		instanceFieldRef byte[] Tim/dataToSign;
		// 51
		instanceFieldRef byte[] Tim/dataSigned;
		// 52
		instanceFieldRef byte[] Tim/tokenKeyData;
		// 53
		instanceFieldRef RequestTokenRW Tim/request_token_key_data;
		// 54
		instanceFieldRef 3.1 Tim/cipherRsaTim;
		// 55
		instanceFieldRef 3.1 Tim/cipherForSignRSA;
		// 56
		instanceFieldRef 2.8 Tim/appPrivKey;
		// 57
		instanceFieldRef 2.8 Tim/timPrivKey;
		// 58
		instanceFieldRef 2.9 Tim/timPubKey;
		// 59
		instanceFieldRef 3.1 Tim/cipherForAESCBC;
		// 60
		instanceFieldRef 2.15 Tim/signature;
		// 61
		instanceFieldRef 2.9 Tim/serverPubKey;
		// 62
		instanceFieldRef 3.1 Tim/cipherRsaServer;
		// 63
		instanceFieldRef 2.16 Tim/keyPair;
		// 64
		instanceFieldRef 2.14 Tim/pseudo_random;
		// 65
		instanceFieldRef byte[] Tim/randomBuffer;
		// 66
		instanceFieldRef byte Tim/currentINS;
		// 67
		instanceFieldRef 2.14 Tim/secure_random;
		// 68
		staticMethodRef 3.1.0(BZ)Ljavacardx/crypto/Cipher;;		// javacardx/crypto/Cipher.getInstance(BZ)Ljavacardx/crypto/Cipher;
			.descriptor	Ljavacardx/crypto/Cipher;	3.1;

		// 69
		staticMethodRef 1.16.1([BS[BSS)S;		// javacard/framework/Util.arrayCopy([BS[BSS)S
		// 70
		virtualMethodRef RequestTokenRW/searchRequest([BS)S;
		// 71
		staticMethodRef 2.13.0(BSZ)Ljavacard/security/Key;;		// javacard/security/KeyBuilder.buildKey(BSZ)Ljavacard/security/Key;
			.descriptor	Ljavacard/security/Key;	2.0;

		// 72
		classRef 2.8;		// javacard/security/RSAPrivateKey
		// 73
		virtualMethodRef RequestTokenRW/compactBlocks(S)S;
		// 74
		virtualMethodRef RequestTokenRW/searchRequest([B)S;
		// 75
		staticFieldRef byte[] Tim/timPrivExponent;
		// 76
		staticFieldRef byte[] Tim/timModulus;
		// 77
		classRef 2.9;		// javacard/security/RSAPublicKey
		// 78
		staticMethodRef 1.16.0([BS[BSS)B;		// javacard/framework/Util.arrayCompare([BS[BSS)B
		// 79
		staticFieldRef byte[] Tim/rsaPublicExponent;
		// 80
		virtualMethodRef 3.1.3(Ljavacard/security/Key;B)V;		// javacardx/crypto/Cipher.init(Ljavacard/security/Key;B)V
			.descriptor	Ljavacard/security/Key;	2.0;

		// 81
		classRef 0.2;		// java/lang/Exception
		// 82
		staticMethodRef 2.15.0(BZ)Ljavacard/security/Signature;;		// javacard/security/Signature.getInstance(BZ)Ljavacard/security/Signature;
			.descriptor	Ljavacard/security/Signature;	2.15;

		// 83
		staticMethodRef 1.3.0()V;		// javacard/framework/Applet.<init>()V
		// 84
		staticMethodRef 0.0.0()V;		// java/lang/Object.<init>()V
		// 85
		staticFieldRef byte[] Tim/keyServerModulus;
		// 86
		virtualMethodRef RequestTokenRW/reset()V;
		// 87
		classRef 2.16;		// javacard/security/KeyPair
		// 88
		staticMethodRef 2.16.0(BS)V;		// javacard/security/KeyPair.<init>(BS)V
		// 89
		staticMethodRef 1.16.6([BSS)S;		// javacard/framework/Util.setShort([BSS)S
		// 90
		staticMethodRef 2.14.0(B)Ljavacard/security/RandomData;;		// javacard/security/RandomData.getInstance(B)Ljavacard/security/RandomData;
			.descriptor	Ljavacard/security/RandomData;	2.14;

		// 91
		staticMethodRef 1.16.4([BS)S;		// javacard/framework/Util.getShort([BS)S
		// 92
		staticFieldRef byte Tim/MAX_RANDOM_LENGTH;
		// 93
		classRef RequestTokenRW;
		// 94
		virtualMethodRef 1.3.1()V;		// javacard/framework/Applet.register()V
		// 95
		classRef Tim;
		// 96
		staticMethodRef Tim/<init>()V;
		// 97
		virtualMethodRef 1.10.1()[B;		// javacard/framework/APDU.getBuffer()[B
		// 98
		virtualMethodRef 1.10.6()S;		// javacard/framework/APDU.setIncomingAndReceive()S
		// 99
		staticMethodRef Tim/setTime([BSS)V;
		// 100
		staticMethodRef Tim/receiveData([BS[B)S;
		// 101
		staticFieldRef byte[] Tim/emptyTimAppKey_Value;
		// 102
		virtualMethodRef Tim/updateTokensAndKeys([BS[BS)Z;
		// 103
		virtualMethodRef RequestTokenRW/searchRequestData([B)S;
		// 104
		staticMethodRef 1.7.1(S)V;		// javacard/framework/ISOException.throwIt(S)V
		// 105
		virtualMethodRef RequestTokenRW/getTokensAndAppKeys(S[BS)S;
		// 106
		virtualMethodRef RequestTokenRW/removeRequestData([B)Z;
		// 107
		staticFieldRef byte[] Tim/TIM_ID;
		// 108
		staticMethodRef Tim/sendData([BSS[BLjavacard/framework/APDU;)S;
			.descriptor	Ljavacard/framework/APDU;	1.10;

		// 109
		staticFieldRef byte[] Tim/TIM_SECRET;
		// 110
		virtualMethodRef RequestTokenRW/getTokensAndPubKey(S[BS)S;
		// 111
		virtualMethodRef RequestTokenRW/getTokens(S[BS)S;
		// 112
		virtualMethodRef RequestTokenRW/getFreeSpace()S;
		// 113
		virtualMethodRef 1.10.7()S;		// javacard/framework/APDU.setOutgoing()S
		// 114
		virtualMethodRef 1.10.9(S)V;		// javacard/framework/APDU.setOutgoingLength(S)V
		// 115
		virtualMethodRef 1.10.5([BSS)V;		// javacard/framework/APDU.sendBytesLong([BSS)V
		// 116
		virtualMethodRef Tim/computeTimTokenSignature()V;
		// 117
		virtualMethodRef 2.15.3(Ljavacard/security/Key;B)V;		// javacard/security/Signature.init(Ljavacard/security/Key;B)V
			.descriptor	Ljavacard/security/Key;	2.0;

		// 118
		virtualMethodRef 2.15.5([BSS[BS)S;		// javacard/security/Signature.sign([BSS[BS)S
		// 119
		virtualMethodRef Tim/makeRO()V;
		// 120
		virtualMethodRef Tim/signRO()V;
		// 121
		virtualMethodRef Tim/signRO1()V;
		// 122
		virtualMethodRef Tim/signRO2()V;
		// 123
		virtualMethodRef Tim/signRO3()V;
		// 124
		virtualMethodRef Tim/signRO4()V;
		// 125
		virtualMethodRef Tim/signRO5()V;
		// 126
		virtualMethodRef Tim/encryptRO()V;
		// 127
		virtualMethodRef Tim/encryptRO1()V;
		// 128
		virtualMethodRef Tim/encryptRO2()V;
		// 129
		virtualMethodRef Tim/encryptRO3()V;
		// 130
		virtualMethodRef Tim/encryptRO4()V;
		// 131
		virtualMethodRef Tim/encryptRO5()V;
		// 132
		virtualMethodRef 2.16.1()V;		// javacard/security/KeyPair.genKeyPair()V
		// 133
		virtualMethodRef 2.16.3()Ljavacard/security/PublicKey;;		// javacard/security/KeyPair.getPublic()Ljavacard/security/PublicKey;
			.descriptor	Ljavacard/security/PublicKey;	2.3;

		// 134
		virtualMethodRef 2.16.2()Ljavacard/security/PrivateKey;;		// javacard/security/KeyPair.getPrivate()Ljavacard/security/PrivateKey;
			.descriptor	Ljavacard/security/PrivateKey;	2.2;

		// 135
		staticFieldRef byte[] Tim/defaultTimAppKey_Modulus;
		// 136
		staticFieldRef byte[] Tim/defaultTimAppKey_privateExponent;
		// 137
		staticMethodRef RequestTokenRW/<init>(S)V;
		// 138
		staticFieldRef byte[] Tim/map64;
		// 139
		staticFieldRef byte[] Tim/_URL_SAFE_DECODABET;
		// 140
		staticFieldRef byte[] Tim/data_client_id;
		// 141
		staticFieldRef byte[] Tim/json_separator;
		// 142
		staticFieldRef byte[] Tim/data_redirect_uri;
		// 143
		staticFieldRef byte[] Tim/data_scope;
		// 144
		staticFieldRef byte[] Tim/data_response_type;
		// 145
		staticFieldRef byte[] Tim/data_tim_params_begin;
		// 146
		staticFieldRef byte[] Tim/data_tim_params_end;
		// 147
		virtualMethodRef Tim/encode64URL([BSS[B)S;
		// 148
		staticFieldRef byte[] Tim/jweHeader64;
		// 149
		staticMethodRef RequestTokenRW/skipParam([BSS)S;
		// 150
		virtualMethodRef 2.14.1([BSS)V;		// javacard/security/RandomData.generateData([BSS)V
		// 151
		virtualMethodRef 3.1.1([BSS[BS)S;		// javacardx/crypto/Cipher.doFinal([BSS[BS)S
		// 152
		classRef 2.20;		// javacard/security/AESKey
		// 153
		virtualMethodRef 3.1.4(Ljavacard/security/Key;B[BSS)V;		// javacardx/crypto/Cipher.init(Ljavacard/security/Key;B[BSS)V
			.descriptor	Ljavacard/security/Key;	2.0;

		// 154
		classRef 2.12;		// javacard/security/CryptoException
		// 155
		virtualMethodRef 1.5.1()S;		// javacard/framework/CardRuntimeException.getReason()S
		// 156
		virtualMethodRef RequestTokenRW/setRequestToken([B[B)Z;
	}

	.class public RequestTokenRW 0 extends 0.0 {		// extends java/lang/Object

		.fields {
			 byte[] tr_buffer 0;		// [B
			static final short ZERO = 0;		// S
			static final short ONE = 1;		// S
			static final short TWO = 2;		// S
			static final short THREE = 3;		// S
			static final short FOUR = 4;		// S
			static final short FIVE = 5;		// S
		}

		.publicMethodTable 1 {
			equals(Ljava/lang/Object;)Z;
			reset()V;
			removeRequestData([B)Z;
		}

		.packageMethodTable 0 {
			getTokens(S[BS)S;
			getTokensAndAppKeys(S[BS)S;
			getTokensAndPubKey(S[BS)S;
			setRequestToken([B[B)Z;
			searchRequestData([B)S;
			searchRequest([B)S;
			searchRequest([BS)S;
			compactBlocks(S)S;
			getFreeSpace()S;
			sign(Ljavacard/security/Key;[B[B)V;
		}

		.method public <init>(S)V 0 {
			.stack 2;
			.locals 0;

				L0:	aload_0;
					invokespecial 84;		// java/lang/Object.<init>()V
					aload_0;
					sload_1;
					newarray 11;
					putfield_a 0;		// reference com/orange/tim/RequestTokenRW.tr_buffer
					aload_0;
					invokevirtual 86;		// com/orange/tim/RequestTokenRW.reset()V
					return;
		}

		.method public reset()V 1 {
			.stack 3;
			.locals 0;

				L0:	getfield_a_this 0;		// reference com/orange/tim/RequestTokenRW.tr_buffer
					sconst_0;
					sconst_0;
					invokestatic 89;		// javacard/framework/Util.setShort([BSS)S
					pop;
					getfield_a_this 0;		// reference com/orange/tim/RequestTokenRW.tr_buffer
					sconst_1;
					sconst_3;
					invokestatic 89;		// javacard/framework/Util.setShort([BSS)S
					pop;
					return;
		}

		.method static skipParam([BSS)S {
			.stack 3;
			.locals 2;

				L0:	sconst_0;
					sstore_3;
				L1:	sconst_0;
					sstore 4;
				L2:	goto L4;
				L3:	aload_0;
					sload_2;
					invokestatic 91;		// javacard/framework/Util.getShort([BS)S
					sstore_3;
					sload_2;
					sload_3;
					sconst_2;
					sadd;
					sadd;
					sstore_2;
					sload 4;
					sconst_1;
					sadd;
					s2b;
					sstore 4;
				L4:	sload 4;
					sload_1;
					if_scmplt L3;
				L5:	sload_2;
					sreturn;
		}

		.method  getTokens(S[BS)S 128 {
			.stack 5;
			.locals 1;

				L0:	getfield_a_this 0;		// reference com/orange/tim/RequestTokenRW.tr_buffer
					sconst_3;
					sload_1;
					invokestatic 149;		// com/orange/tim/RequestTokenRW.skipParam([BSS)S
					sload_1;
					ssub;
					sstore 4;
				L1:	getfield_a_this 0;		// reference com/orange/tim/RequestTokenRW.tr_buffer
					sload_1;
					aload_2;
					sload_3;
					sload 4;
					invokestatic 69;		// javacard/framework/Util.arrayCopy([BS[BSS)S
					pop;
					sload 4;
					sreturn;
		}

		.method  getTokensAndAppKeys(S[BS)S 129 {
			.stack 5;
			.locals 1;

				L0:	getfield_a_this 0;		// reference com/orange/tim/RequestTokenRW.tr_buffer
					sconst_5;
					sload_1;
					invokestatic 149;		// com/orange/tim/RequestTokenRW.skipParam([BSS)S
					sload_1;
					ssub;
					sstore 4;
				L1:	getfield_a_this 0;		// reference com/orange/tim/RequestTokenRW.tr_buffer
					sload_1;
					aload_2;
					sload_3;
					sload 4;
					invokestatic 69;		// javacard/framework/Util.arrayCopy([BS[BSS)S
					pop;
					sload 4;
					sreturn;
		}

		.method  getTokensAndPubKey(S[BS)S 130 {
			.stack 5;
			.locals 1;

				L0:	getfield_a_this 0;		// reference com/orange/tim/RequestTokenRW.tr_buffer
					sconst_4;
					sload_1;
					invokestatic 149;		// com/orange/tim/RequestTokenRW.skipParam([BSS)S
					sload_1;
					ssub;
					sstore 4;
				L1:	getfield_a_this 0;		// reference com/orange/tim/RequestTokenRW.tr_buffer
					sload_1;
					aload_2;
					sload_3;
					sload 4;
					invokestatic 69;		// javacard/framework/Util.arrayCopy([BS[BSS)S
					pop;
					sload 4;
					sreturn;
		}

		.method  setRequestToken([B[B)Z 131 {
			.stack 5;
			.locals 6;

				L0:	aload_1;
					sconst_4;
					sconst_0;
					invokestatic 149;		// com/orange/tim/RequestTokenRW.skipParam([BSS)S
					sstore_3;
				L1:	aload_2;
					sconst_5;
					sconst_0;
					invokestatic 149;		// com/orange/tim/RequestTokenRW.skipParam([BSS)S
					sstore 4;
				L2:	sload_3;
					sload 4;
					sadd;
					sstore 5;
				L3:	aload_0;
					aload_1;
					sload_3;
					invokevirtual 70;		// com/orange/tim/RequestTokenRW.searchRequest([BS)S
					sstore 6;
				L4:	sload 6;
					sconst_m1;
					if_scmpne L8;
				L5:	getfield_a_this 0;		// reference com/orange/tim/RequestTokenRW.tr_buffer
					sconst_1;
					invokestatic 91;		// javacard/framework/Util.getShort([BS)S
					sstore 6;
					getfield_a_this 0;		// reference com/orange/tim/RequestTokenRW.tr_buffer
					arraylength;
					sload 6;
					ssub;
					sload 5;
					if_scmpge L7;
				L6:	sconst_0;
					sreturn;
				L7:	getfield_a_this 0;		// reference com/orange/tim/RequestTokenRW.tr_buffer
					sconst_0;
					dup2;
					baload;
					sconst_1;
					sadd;
					s2b;
					bastore;
					getfield_a_this 0;		// reference com/orange/tim/RequestTokenRW.tr_buffer
					sload 6;
					sload 5;
					invokestatic 89;		// javacard/framework/Util.setShort([BSS)S
					sstore 6;
					aload_1;
					sconst_0;
					getfield_a_this 0;		// reference com/orange/tim/RequestTokenRW.tr_buffer
					sload 6;
					sload_3;
					invokestatic 69;		// javacard/framework/Util.arrayCopy([BS[BSS)S
					sstore 6;
					aload_2;
					sconst_0;
					getfield_a_this 0;		// reference com/orange/tim/RequestTokenRW.tr_buffer
					sload 6;
					sload 4;
					invokestatic 69;		// javacard/framework/Util.arrayCopy([BS[BSS)S
					sstore 6;
					getfield_a_this 0;		// reference com/orange/tim/RequestTokenRW.tr_buffer
					sconst_1;
					sload 6;
					invokestatic 89;		// javacard/framework/Util.setShort([BSS)S
					pop;
					sconst_1;
					sreturn;
				L8:	getfield_a_this 0;		// reference com/orange/tim/RequestTokenRW.tr_buffer
					sload 6;
					invokestatic 91;		// javacard/framework/Util.getShort([BS)S
					sstore 7;
				L9:	sload 7;
					sload 5;
					if_scmpge L14;
				L10:	aload_0;
					sload 6;
					invokevirtual 73;		// com/orange/tim/RequestTokenRW.compactBlocks(S)S
					sstore 6;
					getfield_a_this 0;		// reference com/orange/tim/RequestTokenRW.tr_buffer
					arraylength;
					sload 6;
					ssub;
					sstore 8;
				L11:	sload 8;
					sload 5;
					if_scmpge L13;
				L12:	getfield_a_this 0;		// reference com/orange/tim/RequestTokenRW.tr_buffer
					sconst_1;
					sload 6;
					invokestatic 89;		// javacard/framework/Util.setShort([BSS)S
					pop;
					sconst_0;
					sreturn;
				L13:	getfield_a_this 0;		// reference com/orange/tim/RequestTokenRW.tr_buffer
					sload 6;
					sload 5;
					invokestatic 89;		// javacard/framework/Util.setShort([BSS)S
					sstore 6;
					getfield_a_this 0;		// reference com/orange/tim/RequestTokenRW.tr_buffer
					sconst_1;
					sload 6;
					sload 5;
					sadd;
					invokestatic 89;		// javacard/framework/Util.setShort([BSS)S
					pop;
					aload_1;
					sconst_0;
					getfield_a_this 0;		// reference com/orange/tim/RequestTokenRW.tr_buffer
					sload 6;
					sload_3;
					invokestatic 69;		// javacard/framework/Util.arrayCopy([BS[BSS)S
					sstore 6;
					goto L15;
				L14:	sload 6;
					sconst_2;
					sload_3;
					sadd;
					sadd;
					sstore 6;
				L15:	aload_2;
					sconst_0;
					getfield_a_this 0;		// reference com/orange/tim/RequestTokenRW.tr_buffer
					sload 6;
					sload 4;
					invokestatic 69;		// javacard/framework/Util.arrayCopy([BS[BSS)S
					pop;
					sconst_1;
					sreturn;
		}

		.method public removeRequestData([B)Z 2 {
			.stack 4;
			.locals 1;

				L0:	aload_0;
					aload_1;
					invokevirtual 74;		// com/orange/tim/RequestTokenRW.searchRequest([B)S
					sstore_2;
				L1:	sload_2;
					sconst_m1;
					if_scmpne L3;
				L2:	sconst_0;
					sreturn;
				L3:	aload_0;
					sload_2;
					invokevirtual 73;		// com/orange/tim/RequestTokenRW.compactBlocks(S)S
					sstore_2;
					getfield_a_this 0;		// reference com/orange/tim/RequestTokenRW.tr_buffer
					sconst_1;
					sload_2;
					invokestatic 89;		// javacard/framework/Util.setShort([BSS)S
					pop;
					getfield_a_this 0;		// reference com/orange/tim/RequestTokenRW.tr_buffer
					sconst_0;
					dup2;
					baload;
					sconst_1;
					ssub;
					s2b;
					bastore;
					sconst_1;
					sreturn;
		}

		.method  searchRequestData([B)S 132 {
			.stack 3;
			.locals 2;

				L0:	aload_1;
					sconst_4;
					sconst_0;
					invokestatic 149;		// com/orange/tim/RequestTokenRW.skipParam([BSS)S
					sstore_2;
				L1:	aload_0;
					aload_1;
					sload_2;
					invokevirtual 70;		// com/orange/tim/RequestTokenRW.searchRequest([BS)S
					sstore_3;
				L2:	sload_3;
					sconst_m1;
					if_scmpeq L4;
				L3:	sload_3;
					sload_2;
					sconst_2;
					sadd;
					sadd;
					sstore_3;
				L4:	sload_3;
					sreturn;
		}

		.method  searchRequest([B)S 133 {
			.stack 5;
			.locals 0;

				L0:	aload_0;
					aload_1;
					aload_1;
					sconst_4;
					sconst_0;
					invokestatic 149;		// com/orange/tim/RequestTokenRW.skipParam([BSS)S
					invokevirtual 70;		// com/orange/tim/RequestTokenRW.searchRequest([BS)S
					sreturn;
		}

		.method  searchRequest([BS)S 134 {
			.stack 5;
			.locals 4;

				L0:	getfield_a_this 0;		// reference com/orange/tim/RequestTokenRW.tr_buffer
					sconst_0;
					baload;
					ifle L10;
				L1:	getfield_a_this 0;		// reference com/orange/tim/RequestTokenRW.tr_buffer
					sconst_1;
					invokestatic 91;		// javacard/framework/Util.getShort([BS)S
					sstore_3;
				L2:	sconst_3;
					sstore 4;
				L3:	goto L9;
				L4:	getfield_a_this 0;		// reference com/orange/tim/RequestTokenRW.tr_buffer
					sload 4;
					invokestatic 91;		// javacard/framework/Util.getShort([BS)S
					sstore 5;
				L5:	sload 4;
					sconst_2;
					sadd;
					sstore 6;
				L6:	getfield_a_this 0;		// reference com/orange/tim/RequestTokenRW.tr_buffer
					sload 6;
					aload_1;
					sconst_0;
					sload_2;
					invokestatic 78;		// javacard/framework/Util.arrayCompare([BS[BSS)B
					ifne L8;
				L7:	sload 4;
					sreturn;
				L8:	sload 6;
					sload 5;
					sadd;
					sstore 4;
				L9:	sload 4;
					sload_3;
					if_scmplt L4;
				L10:	sconst_m1;
					sreturn;
		}

		.method  compactBlocks(S)S 135 {
			.stack 5;
			.locals 4;

				L0:	getfield_a_this 0;		// reference com/orange/tim/RequestTokenRW.tr_buffer
					sconst_1;
					invokestatic 91;		// javacard/framework/Util.getShort([BS)S
					sstore_2;
				L1:	getfield_a_this 0;		// reference com/orange/tim/RequestTokenRW.tr_buffer
					sload_1;
					invokestatic 91;		// javacard/framework/Util.getShort([BS)S
					sconst_2;
					sadd;
					sstore_3;
				L2:	sload_1;
					sload_3;
					sadd;
					sstore 4;
				L3:	sload_2;
					sload 4;
					ssub;
					sstore 5;
				L4:	sload 5;
					ifle L6;
				L5:	getfield_a_this 0;		// reference com/orange/tim/RequestTokenRW.tr_buffer
					sload 4;
					getfield_a_this 0;		// reference com/orange/tim/RequestTokenRW.tr_buffer
					sload_1;
					sload 5;
					invokestatic 69;		// javacard/framework/Util.arrayCopy([BS[BSS)S
					sreturn;
				L6:	sload_1;
					sreturn;
		}

		.method  getFreeSpace()S 136 {
			.stack 2;
			.locals 1;

				L0:	getfield_a_this 0;		// reference com/orange/tim/RequestTokenRW.tr_buffer
					ifnonnull L2;
				L1:	sconst_0;
					sreturn;
				L2:	getfield_a_this 0;		// reference com/orange/tim/RequestTokenRW.tr_buffer
					sconst_1;
					invokestatic 91;		// javacard/framework/Util.getShort([BS)S
					sstore_1;
				L3:	getfield_a_this 0;		// reference com/orange/tim/RequestTokenRW.tr_buffer
					arraylength;
					sload_1;
					ssub;
					sreturn;
		}

		.method  sign(Ljavacard/security/Key;[B[B)V 137 {
			.stack 0;
			.locals 0;

			.descriptor	Ljavacard/security/Key;	2.0;

				L0:	return;
		}

	}

	.class public Tim 1 extends 1.3 {		// extends javacard/framework/Applet

		.fields {
			private byte[] currentTime 0;		// [B
			private byte[] tempData 1;		// [B
			private byte[] requestData 2;		// [B
			private byte[] requestObjectData 3;		// [B
			private byte[] encoded64 4;		// [B
			private byte[] encryptData 5;		// [B
			private byte[] requestObjectDataSignature 6;		// [B
			private byte[] signedRequestObjectData 7;		// [B
			private byte[] tokenKeyData 8;		// [B
			private byte[] jweData 9;		// [B
			private byte[] pubKey 10;		// [B
			private byte[] privKey 11;		// [B
			private byte[] timToken 12;		// [B
			private byte[] timTokenSignature 13;		// [B
			private byte[] dataToSign 14;		// [B
			private byte[] dataSigned 15;		// [B
			 RequestTokenRW request_token_key_data 16;		// Lcom/orange/tim/RequestTokenRW;
			private final byte[] tempBuf64 17;		// [B
			private 2.8 timPrivKey 18;		// Ljavacard/security/RSAPrivateKey;
			private 2.9 timPubKey 19;		// Ljavacard/security/RSAPublicKey;
			private 2.9 serverPubKey 20;		// Ljavacard/security/RSAPublicKey;
			private 2.16 keyPair 21;		// Ljavacard/security/KeyPair;
			private 2.8 appPrivKey 22;		// Ljavacard/security/RSAPrivateKey;
			private 3.1 cipherRsaServer 23;		// Ljavacardx/crypto/Cipher;
			private 3.1 cipherRsaTim 24;		// Ljavacardx/crypto/Cipher;
			private 3.1 cipherForSignRSA 25;		// Ljavacardx/crypto/Cipher;
			private 3.1 cipherForAESCBC 26;		// Ljavacardx/crypto/Cipher;
			private 2.15 signature 27;		// Ljavacard/security/Signature;
			private 2.14 pseudo_random 28;		// Ljavacard/security/RandomData;
			private 2.14 secure_random 29;		// Ljavacard/security/RandomData;
			private final byte[] rs256Header 30;		// [B
			private final byte[] rs256HeaderB64 31;		// [B
			private final byte[] sha1withrsaHeaderB64 32;		// [B
			private final byte[] sha256Id 33;		// [B
			private byte[] randomBuffer 34;		// [B
			 byte[] cek 35;		// [B
			 byte[] iv_key 36;		// [B
			 byte[] cryptoErrorK 37;		// [B
			 byte[] cryptoErrorI 38;		// [B
			 byte[] cryptoErrorU 39;		// [B
			 byte[] cryptoErrorV 40;		// [B
			 byte[] cryptoErrorD 41;		// [B
			final byte TIM_SIM_VERSION 42;		// B
			private boolean timeSet 43;		// Z
			 short found_data_length 44;		// S
			 short found_tokenKeyData_length 45;		// S
			 short tokenKeyDataLength 46;		// S
			 short requestDataLength 47;		// S
			 short requestObjectLength 48;		// S
			 short signedRequestObjectLength 49;		// S
			 short jweDataLength 50;		// S
			 short pubKeyLen 51;		// S
			 short privKeyLen 52;		// S
			 short timTokenLen 53;		// S
			 short timTokenSignLen 54;		// S
			 short dataToSignLength 55;		// S
			 short signedDataLength 56;		// S
			private short incomming 57;		// S
			private short received_data_length 58;		// S
			private short sent 59;		// S
			private byte currentINS 60;		// B
			private byte seq 61;		// B
			 short signRO_offset 62;		// S
			 short signature_len 63;		// S
			 short encryptRO_offset 64;		// S
			 short encryptRO_length 65;		// S
			 short encryptRO_encrypt_length 66;		// S
			static final byte TIM_CLA = -128;		// B
			static final byte STORE_DATA = 32;		// B
			static final byte GET_DATA = 48;		// B
			static final byte CHECK_AR = 64;		// B
			static final byte AUTH_USER = 80;		// B
			static final byte MAKE_DATA = 81;		// B
			static final byte SET_TIME = 1;		// B
			static final byte SET_TOKENS = 2;		// B
			static final byte SET_USERINFO = 3;		// B
			static final byte SET_APP_REQ = 4;		// B
			static final byte SET_ID_TOKEN = 5;		// B
			static final byte SET_REFRESH_TOKEN = 6;		// B
			static final byte SET_REQUEST_OBJECT = 7;		// B
			static final byte SET_TIM_TOKEN = 8;		// B
			static final byte UPDATE_TOKENS = 9;		// B
			static final byte SET_RESET = 16;		// B
			static final byte DELETE_TOKENS_KEY = 17;		// B
			static final byte SET_SIGNATURE_DATA = 18;		// B
			static final byte GET_TIM_ID = 1;		// B
			static final byte GET_TIM_RO = 2;		// B
			static final byte GET_REFRESH_TOKEN_WITH_TIM_APP_KEY = 3;		// B
			static final byte GET_ACCESS_TOKEN = 4;		// B
			static final byte GET_USER_INFO = 5;		// B
			static final byte GET_TOKENS_KEY = 7;		// B
			static final byte GET_FREE_SPACE = 9;		// B
			static final byte GET_TIM_SECRET = 10;		// B
			static final byte GET_PUB_KEY = 16;		// B
			static final byte GET_TOKENS = 17;		// B
			static final byte GET_TIM_TKN_SIGN = 18;		// B
			static final byte SEARCH_TOKENS = 19;		// B
			static final byte GET_ALL = 32;		// B
			static final byte GET_TK_ALL = 33;		// B
			static final byte GET_APP_REQ = 34;		// B
			static final byte GET_RO = 35;		// B
			static final byte GET_SIGNED_DATA = 36;		// B
			static final byte GET_VERSION = -16;		// B
			static final byte MAKE_RO = 1;		// B
			static final byte GEN_TIM_APP_KEY = 2;		// B
			static final byte SIGN_TIM_TOKEN = 3;		// B
			static final byte BUILD_RO = 16;		// B
			static final byte SIGN_RO = 17;		// B
			static final byte ENCRYPT_RO = 18;		// B
			static final byte SIGN_RO1 = 33;		// B
			static final byte SIGN_RO2 = 34;		// B
			static final byte SIGN_RO3 = 35;		// B
			static final byte SIGN_RO4 = 36;		// B
			static final byte SIGN_RO5 = 37;		// B
			static final byte ENCRYPT_RO1 = 49;		// B
			static final byte ENCRYPT_RO2 = 50;		// B
			static final byte ENCRYPT_RO3 = 51;		// B
			static final byte ENCRYPT_RO4 = 52;		// B
			static final byte ENCRYPT_RO5 = 53;		// B
			static final short SW_ERROR_SETTING_TIME = -28655;		// S
			static final short SW_NO_CACHED_REQUEST = -28654;		// S
			static final short SW_EXP_TOKEN = -28653;		// S
			static final short SW_WAITFOR_DATA = -28652;		// S
			static final short ZERO = 0;		// S
			static final short ONE = 1;		// S
			static final short TWO = 2;		// S
			static final short THREE = 3;		// S
			static final short FOUR = 4;		// S
			static final byte[] TIM_ID = {84,73,77};		// [B
			static final byte[] TIM_SECRET = {116,105,109,115,101,99,114,101,116};		// [B
			private static final short window = 120;		// S
			private static final byte[] _URL_SAFE_DECODABET = {-9,-9,-9,-9,-9,-9,-9,-9,-9,-5,-5,-9,-9,-5,-9,-9,-9,-9,-9,-9,-9,-9,-9,-9,-9,-9,-9,-9,-9,-9,-9,-9,-5,-9,-9,-9,-9,-9,-9,-9,-9,-9,-9,-9,-9,62,-9,-9,52,53,54,55,56,57,58,59,60,61,-9,-9,-9,-1,-9,-9,-9,0,1,2,3,4,5,6,7,8,9,10,11,12,13,14,15,16,17,18,19,20,21,22,23,24,25,-9,-9,-9,-9,63,-9,26,27,28,29,30,31,32,33,34,35,36,37,38,39,40,41,42,43,44,45,46,47,48,49,50,51,-9,-9,-9,-9,-9,-9,-9,-9,-9,-9,-9,-9,-9,-9,-9,-9,-9,-9,-9,-9,-9,-9,-9,-9,-9,-9,-9,-9,-9,-9,-9,-9,-9,-9,-9,-9,-9,-9,-9,-9,-9,-9,-9,-9,-9,-9,-9,-9,-9,-9,-9,-9,-9,-9,-9,-9,-9,-9,-9,-9,-9,-9,-9,-9,-9,-9,-9,-9,-9,-9,-9,-9,-9,-9,-9,-9,-9,-9,-9,-9,-9,-9,-9,-9,-9,-9,-9,-9,-9,-9,-9,-9,-9,-9,-9,-9,-9,-9,-9,-9,-9,-9,-9,-9,-9,-9,-9,-9,-9,-9,-9,-9,-9,-9,-9,-9,-9,-9,-9,-9,-9,-9,-9,-9,-9,-9,-9,-9,-9,-9,-9,-9,-9};		// [B
			private static final byte EQUALS_SIGN = 61;		// B
			private static final byte WHITE_SPACE_ENC = -5;		// B
			private static final byte EQUALS_SIGN_ENC = -1;		// B
			private static final byte[] map64 = {65,66,67,68,69,70,71,72,73,74,75,76,77,78,79,80,81,82,83,84,85,86,87,88,89,90,97,98,99,100,101,102,103,104,105,106,107,108,109,110,111,112,113,114,115,116,117,118,119,120,121,122,48,49,50,51,52,53,54,55,56,57,45,95};		// [B
			static final byte[] data_client_id = {34,99,108,105,101,110,116,95,105,100,34,58,34};		// [B
			static final byte[] data_redirect_uri = {34,114,101,100,105,114,101,99,116,95,117,114,105,34,58,34};		// [B
			static final byte[] data_scope = {34,115,99,111,112,101,34,58,34};		// [B
			static final byte[] data_response_type = {34,114,101,115,112,111,110,115,101,95,116,121,112,101,34,58,34,99,111,100,101,32,105,100,95,116,111,107,101,110};		// [B
			static final byte[] data_tim_params_begin = {34,116,105,109,34,58,123,34,116,105,109,95,97,112,112,95,107,101,121,34,58,123,34,101,115,115,101,110,116,105,97,108,34,58,116,114,117,101,125,44,34,97,112,112,95,105,100,34,58,123,34,118,97,108,117,101,34,58,34};		// [B
			static final byte[] data_tim_params_end = {34,125,125};		// [B
			static final byte[] json_separator = {34,44};		// [B
			private static final byte[] timPrivExponent = {-99,-42,-91,-121,-12,-126,122,-43,-126,60,-114,-97,27,97,95,97,-26,74,31,25,68,-5,108,-34,-80,-122,27,-1,48,44,-119,75,-57,117,-107,26,100,24,48,69,-117,110,-125,112,-103,-61,65,57,-67,-20,90,-90,9,-56,-44,62,87,54,85,21,-51,102,-38,1};		// [B
			private static final byte[] rsaPublicExponent = {1,0,1};		// [B
			private static final byte[] timModulus = {-66,-2,-108,57,76,52,-36,87,105,111,84,0,-128,68,87,-66,97,-60,-107,0,-77,47,51,82,-52,-46,-101,93,78,123,62,15,-110,42,-120,8,98,2,51,-121,118,-40,-73,-124,-17,109,-115,-100,113,-107,-118,10,84,-122,-35,126,105,61,-125,-78,-7,-18,-113,-45};		// [B
			private static final byte[] keyServerModulus = {-37,124,-20,-26,-65,15,64,-86,108,41,-22,20,119,96,99,-49,116,-55,-111,73,99,90,-93,3,-15,127,124,73,-94,27,-44,-79,59,116,36,51,-117,-40,-16,59,-97,5,24,-67,34,121,-115,67,126,122,-3,-125,88,-94,99,-53,13,-51,86,-14,107,2,-67,-15,111,114,22,42,41,106,8,95,-96,-85,113,94,5,3,-14,-104,-76,124,-77,-34,90,96,36,-98,-40,-25,-37,-58,86,102,-5,-64,-37,-82,68,45,-80,97,-90,19,-41,16,-105,5,-123,-36,-44,126,1,18,29,91,-86,20,-63,42,-89,90,65,8,-3};		// [B
			private static final byte[] defaultTimAppKey_Modulus = {-53,-51,12,23,-5,-83,23,110,-80,-89,-11,5,-54,-60,104,-41,-12,-23,93,-101,97,99,-118,120,-114,-121,35,-65,-53,-106,111,127,1,-118,111,95,-31,-112,59,111,-5,85,30,-27,62,21,-38,-44,-18,-116,58,55,117,77,72,21,-35,-117,-7,58,38,43,-37,-109};		// [B
			private static final byte[] defaultTimAppKey_privateExponent = {86,107,54,107,-99,15,2,-42,-81,22,41,114,49,79,35,-34,31,62,45,-79,75,-108,-72,12,-14,-13,31,23,-97,46,-59,75,-27,-103,-59,-53,-96,-63,82,-97,87,-46,-98,27,58,-116,29,-3,107,89,84,-89,-90,123,-68,-75,-43,-13,41,47,-4,-117,-117,97};		// [B
			private static final byte[] emptyTimAppKey_Value = {0,0,0,0,0,0,0,0,0,0,0,0,0,0,0,0,0,0,0,0,0,0,0,0,0,0,0,0,0,0,0,0,0,0,0,0,0,0,0,0,0,0,0,0,0,0,0,0,0,0,0,0,0,0,0,0,0,0,0,0,0,0,0,0,0};		// [B
			private static byte MAX_RANDOM_LENGTH = 8;		// B
			static final byte[] jweHeader = {123,34,97,108,103,34,58,34,82,83,65,49,95,53,34,44,34,101,110,99,34,58,34,65,49,50,56,67,66,67,45,72,83,50,53,54,34,44,34,99,116,121,34,58,34,74,87,84,34,125};		// [B
			static final byte[] jweHeader64 = {101,121,74,104,98,71,99,105,79,105,74,83,85,48,69,120,88,122,85,105,76,67,74,108,98,109,77,105,79,105,74,66,77,84,73,52,81,48,74,68,76,85,104,84,77,106,85,50,73,105,119,105,89,51,82,53,73,106,111,105,83,108,100,85,73,110,48};		// [B
		}

		.publicMethodTable 7 {
			equals(Ljava/lang/Object;)Z;
			register()V;
			register([BSB)V;
			selectingApplet()Z;
			deselect()V;
			getShareableInterfaceObject(Ljavacard/framework/AID;B)Ljavacard/framework/Shareable;;
			select()Z;
			process(Ljavacard/framework/APDU;)V;
			encode64URL([BSS[B)S;
		}

		.packageMethodTable 0 {
			makeRO()V;
			signRO()V;
			signRO1()V;
			signRO2()V;
			signRO3()V;
			signRO4()V;
			signRO5()V;
			encryptRO()V;
			encryptRO1()V;
			encryptRO2()V;
			encryptRO3()V;
			encryptRO4()V;
			encryptRO5()V;
			computeTimTokenSignature()V;
			updateTokensAndKeys([BS[BS)Z;
		}

		.method private <init>()V {
			.stack 5;
			.locals 1;

				L0:	aload_0;
					invokespecial 83;		// javacard/framework/Applet.<init>()V
					aload_0;
					sconst_1;
					putfield_b 1;		// byte com/orange/tim/Tim.TIM_SIM_VERSION
					aload_0;
					sconst_0;
					putfield_s 2;		// short com/orange/tim/Tim.found_data_length
					aload_0;
					sconst_0;
					putfield_s 3;		// short com/orange/tim/Tim.found_tokenKeyData_length
					aload_0;
					sconst_0;
					putfield_s 4;		// short com/orange/tim/Tim.tokenKeyDataLength
					aload_0;
					sconst_0;
					putfield_s 5;		// short com/orange/tim/Tim.requestDataLength
					aload_0;
					sconst_0;
					putfield_s 6;		// short com/orange/tim/Tim.requestObjectLength
					aload_0;
					sconst_0;
					putfield_s 7;		// short com/orange/tim/Tim.signedRequestObjectLength
					aload_0;
					sconst_0;
					putfield_s 8;		// short com/orange/tim/Tim.jweDataLength
					aload_0;
					sconst_0;
					putfield_s 9;		// short com/orange/tim/Tim.pubKeyLen
					aload_0;
					sconst_0;
					putfield_s 10;		// short com/orange/tim/Tim.privKeyLen
					aload_0;
					sconst_0;
					putfield_s 11;		// short com/orange/tim/Tim.timTokenLen
					aload_0;
					sconst_0;
					putfield_s 12;		// short com/orange/tim/Tim.timTokenSignLen
					aload_0;
					sconst_0;
					putfield_s 13;		// short com/orange/tim/Tim.dataToSignLength
					aload_0;
					sconst_0;
					putfield_s 14;		// short com/orange/tim/Tim.signedDataLength
					aload_0;
					sconst_4;
					newarray 11;
					putfield_a 15;		// reference com/orange/tim/Tim.tempBuf64
					aload_0;
					bspush 29;
					newarray 11;
					dup;
					sconst_0;
					bspush 123;
					bastore;
					dup;
					sconst_1;
					bspush 34;
					bastore;
					dup;
					sconst_2;
					bspush 97;
					bastore;
					dup;
					sconst_3;
					bspush 108;
					bastore;
					dup;
					sconst_4;
					bspush 103;
					bastore;
					dup;
					sconst_5;
					bspush 34;
					bastore;
					dup;
					bspush 6;
					bspush 58;
					bastore;
					dup;
					bspush 7;
					bspush 34;
					bastore;
					dup;
					bspush 8;
					bspush 114;
					bastore;
					dup;
					bspush 9;
					bspush 115;
					bastore;
					dup;
					bspush 10;
					bspush 50;
					bastore;
					dup;
					bspush 11;
					bspush 53;
					bastore;
					dup;
					bspush 12;
					bspush 54;
					bastore;
					dup;
					bspush 13;
					bspush 34;
					bastore;
					dup;
					bspush 14;
					bspush 44;
					bastore;
					dup;
					bspush 15;
					bspush 34;
					bastore;
					dup;
					bspush 16;
					bspush 107;
					bastore;
					dup;
					bspush 17;
					bspush 105;
					bastore;
					dup;
					bspush 18;
					bspush 100;
					bastore;
					dup;
					bspush 19;
					bspush 34;
					bastore;
					dup;
					bspush 20;
					bspush 58;
					bastore;
					dup;
					bspush 21;
					bspush 34;
					bastore;
					dup;
					bspush 22;
					bspush 107;
					bastore;
					dup;
					bspush 23;
					bspush 50;
					bastore;
					dup;
					bspush 24;
					bspush 98;
					bastore;
					dup;
					bspush 25;
					bspush 100;
					bastore;
					dup;
					bspush 26;
					bspush 99;
					bastore;
					dup;
					bspush 27;
					bspush 34;
					bastore;
					dup;
					bspush 28;
					bspush 125;
					bastore;
					putfield_a 16;		// reference com/orange/tim/Tim.rs256Header
					aload_0;
					bspush 39;
					newarray 11;
					dup;
					sconst_0;
					bspush 101;
					bastore;
					dup;
					sconst_1;
					bspush 121;
					bastore;
					dup;
					sconst_2;
					bspush 74;
					bastore;
					dup;
					sconst_3;
					bspush 104;
					bastore;
					dup;
					sconst_4;
					bspush 98;
					bastore;
					dup;
					sconst_5;
					bspush 71;
					bastore;
					dup;
					bspush 6;
					bspush 99;
					bastore;
					dup;
					bspush 7;
					bspush 105;
					bastore;
					dup;
					bspush 8;
					bspush 79;
					bastore;
					dup;
					bspush 9;
					bspush 105;
					bastore;
					dup;
					bspush 10;
					bspush 74;
					bastore;
					dup;
					bspush 11;
					bspush 83;
					bastore;
					dup;
					bspush 12;
					bspush 85;
					bastore;
					dup;
					bspush 13;
					bspush 122;
					bastore;
					dup;
					bspush 14;
					bspush 73;
					bastore;
					dup;
					bspush 15;
					bspush 49;
					bastore;
					dup;
					bspush 16;
					bspush 78;
					bastore;
					dup;
					bspush 17;
					bspush 105;
					bastore;
					dup;
					bspush 18;
					bspush 73;
					bastore;
					dup;
					bspush 19;
					bspush 115;
					bastore;
					dup;
					bspush 20;
					bspush 73;
					bastore;
					dup;
					bspush 21;
					bspush 109;
					bastore;
					dup;
					bspush 22;
					bspush 116;
					bastore;
					dup;
					bspush 23;
					bspush 112;
					bastore;
					dup;
					bspush 24;
					bspush 90;
					bastore;
					dup;
					bspush 25;
					bspush 67;
					bastore;
					dup;
					bspush 26;
					bspush 73;
					bastore;
					dup;
					bspush 27;
					bspush 54;
					bastore;
					dup;
					bspush 28;
					bspush 73;
					bastore;
					dup;
					bspush 29;
					bspush 109;
					bastore;
					dup;
					bspush 30;
					bspush 115;
					bastore;
					dup;
					bspush 31;
					bspush 121;
					bastore;
					dup;
					bspush 32;
					bspush 89;
					bastore;
					dup;
					bspush 33;
					bspush 109;
					bastore;
					dup;
					bspush 34;
					bspush 82;
					bastore;
					dup;
					bspush 35;
					bspush 106;
					bastore;
					dup;
					bspush 36;
					bspush 73;
					bastore;
					dup;
					bspush 37;
					bspush 110;
					bastore;
					dup;
					bspush 38;
					bspush 48;
					bastore;
					putfield_a 17;		// reference com/orange/tim/Tim.rs256HeaderB64
					aload_0;
					bspush 47;
					newarray 11;
					dup;
					sconst_0;
					bspush 101;
					bastore;
					dup;
					sconst_1;
					bspush 121;
					bastore;
					dup;
					sconst_2;
					bspush 74;
					bastore;
					dup;
					sconst_3;
					bspush 104;
					bastore;
					dup;
					sconst_4;
					bspush 98;
					bastore;
					dup;
					sconst_5;
					bspush 71;
					bastore;
					dup;
					bspush 6;
					bspush 99;
					bastore;
					dup;
					bspush 7;
					bspush 105;
					bastore;
					dup;
					bspush 8;
					bspush 79;
					bastore;
					dup;
					bspush 9;
					bspush 105;
					bastore;
					dup;
					bspush 10;
					bspush 74;
					bastore;
					dup;
					bspush 11;
					bspush 84;
					bastore;
					dup;
					bspush 12;
					bspush 83;
					bastore;
					dup;
					bspush 13;
					bspush 69;
					bastore;
					dup;
					bspush 14;
					bspush 69;
					bastore;
					dup;
					bspush 15;
					bspush 120;
					bastore;
					dup;
					bspush 16;
					bspush 100;
					bastore;
					dup;
					bspush 17;
					bspush 50;
					bastore;
					dup;
					bspush 18;
					bspush 108;
					bastore;
					dup;
					bspush 19;
					bspush 48;
					bastore;
					dup;
					bspush 20;
					bspush 97;
					bastore;
					dup;
					bspush 21;
					bspush 70;
					bastore;
					dup;
					bspush 22;
					bspush 74;
					bastore;
					dup;
					bspush 23;
					bspush 84;
					bastore;
					dup;
					bspush 24;
					bspush 81;
					bastore;
					dup;
					bspush 25;
					bspush 83;
					bastore;
					dup;
					bspush 26;
					bspush 73;
					bastore;
					dup;
					bspush 27;
					bspush 115;
					bastore;
					dup;
					bspush 28;
					bspush 73;
					bastore;
					dup;
					bspush 29;
					bspush 109;
					bastore;
					dup;
					bspush 30;
					bspush 116;
					bastore;
					dup;
					bspush 31;
					bspush 112;
					bastore;
					dup;
					bspush 32;
					bspush 90;
					bastore;
					dup;
					bspush 33;
					bspush 67;
					bastore;
					dup;
					bspush 34;
					bspush 73;
					bastore;
					dup;
					bspush 35;
					bspush 54;
					bastore;
					dup;
					bspush 36;
					bspush 73;
					bastore;
					dup;
					bspush 37;
					bspush 109;
					bastore;
					dup;
					bspush 38;
					bspush 115;
					bastore;
					dup;
					bspush 39;
					bspush 121;
					bastore;
					dup;
					bspush 40;
					bspush 89;
					bastore;
					dup;
					bspush 41;
					bspush 109;
					bastore;
					dup;
					bspush 42;
					bspush 82;
					bastore;
					dup;
					bspush 43;
					bspush 106;
					bastore;
					dup;
					bspush 44;
					bspush 73;
					bastore;
					dup;
					bspush 45;
					bspush 110;
					bastore;
					dup;
					bspush 46;
					bspush 48;
					bastore;
					putfield_a 18;		// reference com/orange/tim/Tim.sha1withrsaHeaderB64
					aload_0;
					bspush 19;
					newarray 11;
					dup;
					sconst_0;
					bspush 48;
					bastore;
					dup;
					sconst_1;
					bspush 49;
					bastore;
					dup;
					sconst_2;
					bspush 48;
					bastore;
					dup;
					sconst_3;
					bspush 13;
					bastore;
					dup;
					sconst_4;
					bspush 6;
					bastore;
					dup;
					sconst_5;
					bspush 9;
					bastore;
					dup;
					bspush 6;
					bspush 96;
					bastore;
					dup;
					bspush 7;
					bspush -122;
					bastore;
					dup;
					bspush 8;
					bspush 72;
					bastore;
					dup;
					bspush 9;
					sconst_1;
					bastore;
					dup;
					bspush 10;
					bspush 101;
					bastore;
					dup;
					bspush 11;
					sconst_3;
					bastore;
					dup;
					bspush 12;
					sconst_4;
					bastore;
					dup;
					bspush 13;
					sconst_2;
					bastore;
					dup;
					bspush 14;
					sconst_1;
					bastore;
					dup;
					bspush 15;
					sconst_5;
					bastore;
					dup;
					bspush 17;
					sconst_4;
					bastore;
					dup;
					bspush 18;
					bspush 32;
					bastore;
					putfield_a 19;		// reference com/orange/tim/Tim.sha256Id
					aload_0;
					sconst_0;
					putfield_s 20;		// short com/orange/tim/Tim.signRO_offset
					aload_0;
					sconst_0;
					putfield_s 21;		// short com/orange/tim/Tim.signature_len
					aload_0;
					sconst_0;
					putfield_s 22;		// short com/orange/tim/Tim.encryptRO_offset
					aload_0;
					sconst_0;
					putfield_s 23;		// short com/orange/tim/Tim.encryptRO_length
					aload_0;
					sconst_0;
					putfield_s 24;		// short com/orange/tim/Tim.encryptRO_encrypt_length
					aload_0;
					bspush 32;
					newarray 11;
					putfield_a 25;		// reference com/orange/tim/Tim.cek
					aload_0;
					bspush 16;
					newarray 11;
					putfield_a 26;		// reference com/orange/tim/Tim.iv_key
					aload_0;
					sconst_3;
					newarray 11;
					dup;
					sconst_0;
					bspush 75;
					bastore;
					dup;
					sconst_1;
					bspush 69;
					bastore;
					dup;
					sconst_2;
					bspush 89;
					bastore;
					putfield_a 27;		// reference com/orange/tim/Tim.cryptoErrorK
					aload_0;
					sconst_3;
					newarray 11;
					dup;
					sconst_0;
					bspush 73;
					bastore;
					dup;
					sconst_1;
					bspush 78;
					bastore;
					dup;
					sconst_2;
					bspush 73;
					bastore;
					putfield_a 28;		// reference com/orange/tim/Tim.cryptoErrorI
					aload_0;
					sconst_3;
					newarray 11;
					dup;
					sconst_0;
					bspush 85;
					bastore;
					dup;
					sconst_1;
					bspush 83;
					bastore;
					dup;
					sconst_2;
					bspush 69;
					bastore;
					putfield_a 29;		// reference com/orange/tim/Tim.cryptoErrorU
					aload_0;
					sconst_3;
					newarray 11;
					dup;
					sconst_0;
					bspush 86;
					bastore;
					dup;
					sconst_1;
					bspush 65;
					bastore;
					dup;
					sconst_2;
					bspush 76;
					bastore;
					putfield_a 30;		// reference com/orange/tim/Tim.cryptoErrorV
					aload_0;
					sconst_3;
					newarray 11;
					dup;
					sconst_0;
					bspush 68;
					bastore;
					dup;
					sconst_1;
					bspush 69;
					bastore;
					dup;
					sconst_2;
					bspush 70;
					bastore;
					putfield_a 31;		// reference com/orange/tim/Tim.cryptoErrorD
					aload_0;
					sconst_0;
					putfield_b 32;		// boolean com/orange/tim/Tim.timeSet
					aload_0;
					sconst_4;
					newarray 11;
					putfield_a 33;		// reference com/orange/tim/Tim.currentTime
					aload_0;
					sspush 2048;
					newarray 11;
					putfield_a 34;		// reference com/orange/tim/Tim.tempData
					aload_0;
					sconst_0;
					putfield_s 35;		// short com/orange/tim/Tim.incomming
					aload_0;
					sconst_0;
					putfield_s 36;		// short com/orange/tim/Tim.received_data_length
					aload_0;
					sconst_0;
					putfield_s 37;		// short com/orange/tim/Tim.sent
					aload_0;
					sconst_0;
					putfield_b 38;		// byte com/orange/tim/Tim.seq
					aload_0;
					sspush 1024;
					newarray 11;
					putfield_a 39;		// reference com/orange/tim/Tim.requestData
					aload_0;
					sspush 2048;
					newarray 11;
					putfield_a 40;		// reference com/orange/tim/Tim.requestObjectData
					aload_0;
					sspush 2048;
					newarray 11;
					putfield_a 41;		// reference com/orange/tim/Tim.encoded64
					aload_0;
					sspush 2048;
					newarray 11;
					putfield_a 42;		// reference com/orange/tim/Tim.encryptData
					aload_0;
					sspush 1024;
					newarray 11;
					putfield_a 43;		// reference com/orange/tim/Tim.requestObjectDataSignature
					aload_0;
					sspush 2048;
					newarray 11;
					putfield_a 44;		// reference com/orange/tim/Tim.signedRequestObjectData
					aload_0;
					sspush 2048;
					newarray 11;
					putfield_a 45;		// reference com/orange/tim/Tim.jweData
					aload_0;
					sspush 128;
					newarray 11;
					putfield_a 46;		// reference com/orange/tim/Tim.pubKey
					aload_0;
					sspush 128;
					newarray 11;
					putfield_a 47;		// reference com/orange/tim/Tim.privKey
					aload_0;
					sspush 256;
					newarray 11;
					putfield_a 48;		// reference com/orange/tim/Tim.timToken
					aload_0;
					sspush 256;
					newarray 11;
					putfield_a 49;		// reference com/orange/tim/Tim.timTokenSignature
					aload_0;
					sspush 2048;
					newarray 11;
					putfield_a 50;		// reference com/orange/tim/Tim.dataToSign
					aload_0;
					sspush 128;
					newarray 11;
					putfield_a 51;		// reference com/orange/tim/Tim.dataSigned
					aload_0;
					sspush 2000;
					newarray 11;
					putfield_a 52;		// reference com/orange/tim/Tim.tokenKeyData
					aload_0;
					new 93;		// com/orange/tim/RequestTokenRW
					dup;
					sspush 8192;
					invokespecial 137;		// com/orange/tim/RequestTokenRW.<init>(S)V
					putfield_a 53;		// reference com/orange/tim/Tim.request_token_key_data
					aload_0;
					bspush 10;
					sconst_0;
					invokestatic 68;		// javacardx/crypto/Cipher.getInstance(BZ)Ljavacardx/crypto/Cipher;
					putfield_a 54;		// reference com/orange/tim/Tim.cipherRsaTim
					aload_0;
					bspush 10;
					sconst_0;
					invokestatic 68;		// javacardx/crypto/Cipher.getInstance(BZ)Ljavacardx/crypto/Cipher;
					putfield_a 55;		// reference com/orange/tim/Tim.cipherForSignRSA
					aload_0;
					sconst_5;
					sspush 512;
					sconst_0;
					invokestatic 71;		// javacard/security/KeyBuilder.buildKey(BSZ)Ljavacard/security/Key;
					checkcast 0 72;		// T_CLASSORINTERFACE javacard/security/RSAPrivateKey
					putfield_a 56;		// reference com/orange/tim/Tim.appPrivKey
					aload_0;
					sconst_5;
					sspush 512;
					sconst_0;
					invokestatic 71;		// javacard/security/KeyBuilder.buildKey(BSZ)Ljavacard/security/Key;
					checkcast 0 72;		// T_CLASSORINTERFACE javacard/security/RSAPrivateKey
					putfield_a 57;		// reference com/orange/tim/Tim.timPrivKey
					getfield_a_this 57;		// reference com/orange/tim/Tim.timPrivKey
					getstatic_a 75;		// reference com/orange/tim/Tim.timPrivExponent
					sconst_0;
					getstatic_a 75;		// reference com/orange/tim/Tim.timPrivExponent
					arraylength;
					invokeinterface 4 72 6;		// javacard/security/RSAPrivateKey
					getfield_a_this 57;		// reference com/orange/tim/Tim.timPrivKey
					getstatic_a 76;		// reference com/orange/tim/Tim.timModulus
					sconst_0;
					getstatic_a 76;		// reference com/orange/tim/Tim.timModulus
					arraylength;
					invokeinterface 4 72 7;		// javacard/security/RSAPrivateKey
					aload_0;
					sconst_4;
					sspush 512;
					sconst_0;
					invokestatic 71;		// javacard/security/KeyBuilder.buildKey(BSZ)Ljavacard/security/Key;
					checkcast 0 77;		// T_CLASSORINTERFACE javacard/security/RSAPublicKey
					putfield_a 58;		// reference com/orange/tim/Tim.timPubKey
					getfield_a_this 58;		// reference com/orange/tim/Tim.timPubKey
					getstatic_a 79;		// reference com/orange/tim/Tim.rsaPublicExponent
					sconst_0;
					getstatic_a 79;		// reference com/orange/tim/Tim.rsaPublicExponent
					arraylength;
					invokeinterface 4 77 6;		// javacard/security/RSAPublicKey
					getfield_a_this 58;		// reference com/orange/tim/Tim.timPubKey
					getstatic_a 76;		// reference com/orange/tim/Tim.timModulus
					sconst_0;
					getstatic_a 76;		// reference com/orange/tim/Tim.timModulus
					arraylength;
					invokeinterface 4 77 7;		// javacard/security/RSAPublicKey
					getfield_a_this 54;		// reference com/orange/tim/Tim.cipherRsaTim
					getfield_a_this 58;		// reference com/orange/tim/Tim.timPubKey
					sconst_2;
					invokevirtual 80;		// javacardx/crypto/Cipher.init(Ljavacard/security/Key;B)V
					getfield_a_this 55;		// reference com/orange/tim/Tim.cipherForSignRSA
					getfield_a_this 57;		// reference com/orange/tim/Tim.timPrivKey
					sconst_2;
					invokevirtual 80;		// javacardx/crypto/Cipher.init(Ljavacard/security/Key;B)V
					aload_0;
					bspush 13;
					sconst_0;
					invokestatic 68;		// javacardx/crypto/Cipher.getInstance(BZ)Ljavacardx/crypto/Cipher;
					putfield_a 59;		// reference com/orange/tim/Tim.cipherForAESCBC
					aload_0;
					bspush 10;
					sconst_0;
					invokestatic 82;		// javacard/security/Signature.getInstance(BZ)Ljavacard/security/Signature;
					putfield_a 60;		// reference com/orange/tim/Tim.signature
				L1:	aload_0;
					sconst_4;
					sspush 1024;
					sconst_0;
					invokestatic 71;		// javacard/security/KeyBuilder.buildKey(BSZ)Ljavacard/security/Key;
					checkcast 0 77;		// T_CLASSORINTERFACE javacard/security/RSAPublicKey
					putfield_a 61;		// reference com/orange/tim/Tim.serverPubKey
					getfield_a_this 61;		// reference com/orange/tim/Tim.serverPubKey
					getstatic_a 79;		// reference com/orange/tim/Tim.rsaPublicExponent
					sconst_0;
					getstatic_a 79;		// reference com/orange/tim/Tim.rsaPublicExponent
					arraylength;
					invokeinterface 4 77 6;		// javacard/security/RSAPublicKey
					getfield_a_this 61;		// reference com/orange/tim/Tim.serverPubKey
					getstatic_a 85;		// reference com/orange/tim/Tim.keyServerModulus
					sconst_0;
					getstatic_a 85;		// reference com/orange/tim/Tim.keyServerModulus
					arraylength;
					invokeinterface 4 77 7;		// javacard/security/RSAPublicKey
					aload_0;
					bspush 10;
					sconst_0;
					invokestatic 68;		// javacardx/crypto/Cipher.getInstance(BZ)Ljavacardx/crypto/Cipher;
					putfield_a 62;		// reference com/orange/tim/Tim.cipherRsaServer
					getfield_a_this 62;		// reference com/orange/tim/Tim.cipherRsaServer
					getfield_a_this 61;		// reference com/orange/tim/Tim.serverPubKey
					sconst_2;
					invokevirtual 80;		// javacardx/crypto/Cipher.init(Ljavacard/security/Key;B)V
					aload_0;
					new 87;		// javacard/security/KeyPair
					dup;
					sconst_2;
					sspush 512;
					invokespecial 88;		// javacard/security/KeyPair.<init>(BS)V
					putfield_a 63;		// reference com/orange/tim/Tim.keyPair
				L2:	goto L4;
				L3:	astore_1;
				L4:	aload_0;
					sconst_1;
					invokestatic 90;		// javacard/security/RandomData.getInstance(B)Ljavacard/security/RandomData;
					putfield_a 64;		// reference com/orange/tim/Tim.pseudo_random
					aload_0;
					getstatic_b 92;		// byte com/orange/tim/Tim.MAX_RANDOM_LENGTH
					newarray 11;
					putfield_a 65;		// reference com/orange/tim/Tim.randomBuffer
					aload_0;
					invokevirtual 94;		// javacard/framework/Applet.register()V
					return;
			.exceptionTable {
				// start_block end_block handler_block catch_type_index
				L1 L2 L3 81;
			}
		}

		.method public static install([BSB)V 0 {
			.stack 1;
			.locals 0;

				L0:	new 95;		// com/orange/tim/Tim
					invokespecial 96;		// com/orange/tim/Tim.<init>()V
					return;
		}

		.method public process(Ljavacard/framework/APDU;)V 7 {
			.stack 7;
			.locals 4;

			.descriptor	Ljavacard/framework/APDU;	1.10;

				L0:	aload_1;
					invokevirtual 97;		// javacard/framework/APDU.getBuffer()[B
					astore_2;
				L1:	aload_1;
					invokevirtual 98;		// javacard/framework/APDU.setIncomingAndReceive()S
					sstore_3;
				L2:	aload_2;
					sconst_1;
					baload;
					slookupswitch L122 5 32 L3 48 L41 64 L90 80 L91 81 L92;
				L3:	aload_2;
					sconst_2;
					baload;
					stableswitch L40 1 18 L4 L11 L22 L5 L40 L40 L23 L28 L15 L40 L40 L40 L40 L40 L40 L34 L32 L35;
				L4:	aload_0;
					aload_2;
					sconst_5;
					sload_3;
					invokespecial 99;		// com/orange/tim/Tim.setTime([BSS)V
					goto_w L122;
				L5:	aload_2;
					sconst_3;
					baload;
					ifne L7;
				L6:	aload_0;
					sconst_0;
					putfield_s 5;		// short com/orange/tim/Tim.requestDataLength
					aload_0;
					sconst_0;
					putfield_s 7;		// short com/orange/tim/Tim.signedRequestObjectLength
					aload_0;
					sconst_0;
					putfield_s 8;		// short com/orange/tim/Tim.jweDataLength
					aload_0;
					sconst_0;
					putfield_s 3;		// short com/orange/tim/Tim.found_tokenKeyData_length
					aload_0;
					sconst_0;
					putfield_s 4;		// short com/orange/tim/Tim.tokenKeyDataLength
					aload_0;
					sconst_0;
					putfield_s 2;		// short com/orange/tim/Tim.found_data_length
				L7:	aload_0;
					aload_2;
					sload_3;
					getfield_a_this 39;		// reference com/orange/tim/Tim.requestData
					invokespecial 100;		// com/orange/tim/Tim.receiveData([BS[B)S
					sstore 4;
				L8:	sload 4;
					sconst_m1;
					if_scmpeq_w L122;
				L9:	aload_0;
					getfield_s_this 36;		// short com/orange/tim/Tim.received_data_length
					putfield_s 5;		// short com/orange/tim/Tim.requestDataLength
				L10:	goto_w L122;
				L11:	aload_0;
					aload_2;
					sload_3;
					getfield_a_this 52;		// reference com/orange/tim/Tim.tokenKeyData
					invokespecial 100;		// com/orange/tim/Tim.receiveData([BS[B)S
					sstore 4;
				L12:	sload 4;
					sconst_m1;
					if_scmpeq_w L122;
				L13:	aload_0;
					getfield_s_this 36;		// short com/orange/tim/Tim.received_data_length
					putfield_s 4;		// short com/orange/tim/Tim.tokenKeyDataLength
					aload_0;
					getstatic_a 101;		// reference com/orange/tim/Tim.emptyTimAppKey_Value
					getstatic_a 101;		// reference com/orange/tim/Tim.emptyTimAppKey_Value
					arraylength;
					getstatic_a 101;		// reference com/orange/tim/Tim.emptyTimAppKey_Value
					getstatic_a 101;		// reference com/orange/tim/Tim.emptyTimAppKey_Value
					arraylength;
					invokevirtual 102;		// com/orange/tim/Tim.updateTokensAndKeys([BS[BS)Z
					pop;
				L14:	goto_w L122;
				L15:	aload_0;
					aload_2;
					sload_3;
					getfield_a_this 52;		// reference com/orange/tim/Tim.tokenKeyData
					invokespecial 100;		// com/orange/tim/Tim.receiveData([BS[B)S
					sstore 4;
				L16:	sload 4;
					sconst_m1;
					if_scmpeq_w L122;
				L17:	aload_0;
					getfield_s_this 36;		// short com/orange/tim/Tim.received_data_length
					putfield_s 4;		// short com/orange/tim/Tim.tokenKeyDataLength
					getfield_a_this 53;		// reference com/orange/tim/Tim.request_token_key_data
					getfield_a_this 39;		// reference com/orange/tim/Tim.requestData
					invokevirtual 103;		// com/orange/tim/RequestTokenRW.searchRequestData([B)S
					sstore 5;
				L18:	sload 5;
					sconst_m1;
					if_scmpne L20;
				L19:	sspush 27267;
					invokestatic 104;		// javacard/framework/ISOException.throwIt(S)V
				L20:	getfield_a_this 53;		// reference com/orange/tim/Tim.request_token_key_data
					sload 5;
					getfield_a_this 34;		// reference com/orange/tim/Tim.tempData
					sconst_0;
					invokevirtual 105;		// com/orange/tim/RequestTokenRW.getTokensAndAppKeys(S[BS)S
					pop;
					getfield_a_this 34;		// reference com/orange/tim/Tim.tempData
					sconst_3;
					sconst_0;
					invokestatic 149;		// com/orange/tim/RequestTokenRW.skipParam([BSS)S
					sstore 5;
					aload_0;
					getfield_a_this 34;		// reference com/orange/tim/Tim.tempData
					sload 5;
					invokestatic 91;		// javacard/framework/Util.getShort([BS)S
					putfield_s 9;		// short com/orange/tim/Tim.pubKeyLen
					sinc 5 2;
					getfield_a_this 34;		// reference com/orange/tim/Tim.tempData
					sload 5;
					getfield_a_this 46;		// reference com/orange/tim/Tim.pubKey
					sconst_0;
					getfield_s_this 9;		// short com/orange/tim/Tim.pubKeyLen
					invokestatic 69;		// javacard/framework/Util.arrayCopy([BS[BSS)S
					pop;
					sload 5;
					getfield_s_this 9;		// short com/orange/tim/Tim.pubKeyLen
					sadd;
					sstore 5;
					aload_0;
					getfield_a_this 34;		// reference com/orange/tim/Tim.tempData
					sload 5;
					invokestatic 91;		// javacard/framework/Util.getShort([BS)S
					putfield_s 10;		// short com/orange/tim/Tim.privKeyLen
					sinc 5 2;
					getfield_a_this 34;		// reference com/orange/tim/Tim.tempData
					sload 5;
					getfield_a_this 47;		// reference com/orange/tim/Tim.privKey
					sconst_0;
					getfield_s_this 10;		// short com/orange/tim/Tim.privKeyLen
					invokestatic 69;		// javacard/framework/Util.arrayCopy([BS[BSS)S
					pop;
					aload_0;
					getfield_a_this 46;		// reference com/orange/tim/Tim.pubKey
					getfield_s_this 9;		// short com/orange/tim/Tim.pubKeyLen
					getfield_a_this 47;		// reference com/orange/tim/Tim.privKey
					getfield_s_this 10;		// short com/orange/tim/Tim.privKeyLen
					invokevirtual 102;		// com/orange/tim/Tim.updateTokensAndKeys([BS[BS)Z
					pop;
				L21:	goto_w L122;
				L22:	goto_w L122;
				L23:	aload_0;
					aload_2;
					sload_3;
					getfield_a_this 40;		// reference com/orange/tim/Tim.requestObjectData
					invokespecial 100;		// com/orange/tim/Tim.receiveData([BS[B)S
					sstore 4;
				L24:	sload 4;
					sconst_m1;
					if_scmpne L26;
				L25:	aload_0;
					sconst_0;
					putfield_s 6;		// short com/orange/tim/Tim.requestObjectLength
					goto_w L122;
				L26:	aload_0;
					getfield_s_this 36;		// short com/orange/tim/Tim.received_data_length
					putfield_s 6;		// short com/orange/tim/Tim.requestObjectLength
				L27:	goto_w L122;
				L28:	aload_0;
					sconst_0;
					putfield_s 11;		// short com/orange/tim/Tim.timTokenLen
					aload_0;
					sconst_0;
					putfield_s 12;		// short com/orange/tim/Tim.timTokenSignLen
					aload_0;
					aload_2;
					sload_3;
					getfield_a_this 48;		// reference com/orange/tim/Tim.timToken
					invokespecial 100;		// com/orange/tim/Tim.receiveData([BS[B)S
					sstore 4;
				L29:	sload 4;
					sconst_m1;
					if_scmpeq_w L122;
				L30:	aload_0;
					getfield_s_this 36;		// short com/orange/tim/Tim.received_data_length
					putfield_s 11;		// short com/orange/tim/Tim.timTokenLen
				L31:	goto_w L122;
				L32:	getfield_a_this 53;		// reference com/orange/tim/Tim.request_token_key_data
					getfield_a_this 39;		// reference com/orange/tim/Tim.requestData
					invokevirtual 106;		// com/orange/tim/RequestTokenRW.removeRequestData([B)Z
					ifne_w L122;
				L33:	sspush 27267;
					invokestatic 104;		// javacard/framework/ISOException.throwIt(S)V
					goto_w L122;
				L34:	getfield_a_this 53;		// reference com/orange/tim/Tim.request_token_key_data
					invokevirtual 86;		// com/orange/tim/RequestTokenRW.reset()V
					goto_w L122;
				L35:	aload_0;
					aload_2;
					sload_3;
					getfield_a_this 50;		// reference com/orange/tim/Tim.dataToSign
					invokespecial 100;		// com/orange/tim/Tim.receiveData([BS[B)S
					sstore 4;
				L36:	sload 4;
					sconst_m1;
					if_scmpne L38;
				L37:	aload_0;
					sconst_0;
					putfield_s 13;		// short com/orange/tim/Tim.dataToSignLength
					aload_0;
					sconst_0;
					putfield_s 14;		// short com/orange/tim/Tim.signedDataLength
					goto_w L122;
				L38:	aload_0;
					getfield_s_this 36;		// short com/orange/tim/Tim.received_data_length
					putfield_s 13;		// short com/orange/tim/Tim.dataToSignLength
				L39:	goto_w L122;
				L40:	sspush 27270;
					invokestatic 104;		// javacard/framework/ISOException.throwIt(S)V
					goto_w L122;
				L41:	aload_2;
					sconst_2;
					baload;
					slookupswitch L89 18 -16 L88 1 L42 2 L44 3 L47 4 L69 5 L70 7 L56 9 L71 10 L43 16 L72 17 L60 18 L73 19 L48 32 L79 33 L53 34 L54 35 L55 36 L80;
				L42:	aload_0;
					getstatic_a 107;		// reference com/orange/tim/Tim.TIM_ID
					sconst_0;
					getstatic_a 107;		// reference com/orange/tim/Tim.TIM_ID
					arraylength;
					aload_2;
					aload_1;
					invokespecial 108;		// com/orange/tim/Tim.sendData([BSS[BLjavacard/framework/APDU;)S
					sstore 4;
					goto_w L122;
				L43:	aload_0;
					getstatic_a 109;		// reference com/orange/tim/Tim.TIM_SECRET
					sconst_0;
					getstatic_a 109;		// reference com/orange/tim/Tim.TIM_SECRET
					arraylength;
					aload_2;
					aload_1;
					invokespecial 108;		// com/orange/tim/Tim.sendData([BSS[BLjavacard/framework/APDU;)S
					sstore 4;
					goto_w L122;
				L44:	getfield_s_this 8;		// short com/orange/tim/Tim.jweDataLength
					ifne L46;
				L45:	sspush 27267;
					invokestatic 104;		// javacard/framework/ISOException.throwIt(S)V
				L46:	aload_0;
					getfield_a_this 45;		// reference com/orange/tim/Tim.jweData
					sconst_0;
					getfield_s_this 8;		// short com/orange/tim/Tim.jweDataLength
					aload_2;
					aload_1;
					invokespecial 108;		// com/orange/tim/Tim.sendData([BSS[BLjavacard/framework/APDU;)S
					sstore 4;
					goto_w L122;
				L47:	goto_w L122;
				L48:	getfield_a_this 53;		// reference com/orange/tim/Tim.request_token_key_data
					getfield_a_this 39;		// reference com/orange/tim/Tim.requestData
					invokevirtual 103;		// com/orange/tim/RequestTokenRW.searchRequestData([B)S
					sstore 4;
				L49:	aload_0;
					sconst_0;
					putfield_s 3;		// short com/orange/tim/Tim.found_tokenKeyData_length
					sload 4;
					sconst_m1;
					if_scmpeq L51;
				L50:	aload_0;
					getfield_a_this 53;		// reference com/orange/tim/Tim.request_token_key_data
					sload 4;
					getfield_a_this 52;		// reference com/orange/tim/Tim.tokenKeyData
					sconst_0;
					invokevirtual 110;		// com/orange/tim/RequestTokenRW.getTokensAndPubKey(S[BS)S
					putfield_s 3;		// short com/orange/tim/Tim.found_tokenKeyData_length
					aload_0;
					getfield_s_this 3;		// short com/orange/tim/Tim.found_tokenKeyData_length
					putfield_s 4;		// short com/orange/tim/Tim.tokenKeyDataLength
					goto_w L122;
				L51:	sspush 27267;
					invokestatic 104;		// javacard/framework/ISOException.throwIt(S)V
				L52:	goto_w L122;
				L53:	aload_0;
					getfield_a_this 52;		// reference com/orange/tim/Tim.tokenKeyData
					sconst_0;
					getfield_a_this 52;		// reference com/orange/tim/Tim.tokenKeyData
					arraylength;
					aload_2;
					aload_1;
					invokespecial 108;		// com/orange/tim/Tim.sendData([BSS[BLjavacard/framework/APDU;)S
					pop;
					goto_w L122;
				L54:	aload_0;
					getfield_a_this 39;		// reference com/orange/tim/Tim.requestData
					sconst_0;
					getfield_a_this 39;		// reference com/orange/tim/Tim.requestData
					arraylength;
					aload_2;
					aload_1;
					invokespecial 108;		// com/orange/tim/Tim.sendData([BSS[BLjavacard/framework/APDU;)S
					pop;
					goto_w L122;
				L55:	aload_0;
					getfield_a_this 40;		// reference com/orange/tim/Tim.requestObjectData
					sconst_0;
					getfield_s_this 6;		// short com/orange/tim/Tim.requestObjectLength
					aload_2;
					aload_1;
					invokespecial 108;		// com/orange/tim/Tim.sendData([BSS[BLjavacard/framework/APDU;)S
					pop;
					goto_w L122;
				L56:	getfield_s_this 3;		// short com/orange/tim/Tim.found_tokenKeyData_length
					ifle L59;
				L57:	aload_0;
					getfield_a_this 52;		// reference com/orange/tim/Tim.tokenKeyData
					sconst_0;
					getfield_s_this 3;		// short com/orange/tim/Tim.found_tokenKeyData_length
					aload_2;
					aload_1;
					invokespecial 108;		// com/orange/tim/Tim.sendData([BSS[BLjavacard/framework/APDU;)S
					sstore 4;
				L58:	goto_w L122;
				L59:	sspush 27267;
					invokestatic 104;		// javacard/framework/ISOException.throwIt(S)V
					goto_w L122;
				L60:	aload_2;
					sconst_3;
					baload;
					ifne L65;
				L61:	getfield_a_this 53;		// reference com/orange/tim/Tim.request_token_key_data
					getfield_a_this 39;		// reference com/orange/tim/Tim.requestData
					invokevirtual 103;		// com/orange/tim/RequestTokenRW.searchRequestData([B)S
					sstore 4;
				L62:	aload_0;
					sconst_0;
					putfield_s 3;		// short com/orange/tim/Tim.found_tokenKeyData_length
					sload 4;
					sconst_m1;
					if_scmpeq L64;
				L63:	aload_0;
					getfield_a_this 53;		// reference com/orange/tim/Tim.request_token_key_data
					sload 4;
					getfield_a_this 52;		// reference com/orange/tim/Tim.tokenKeyData
					sconst_0;
					invokevirtual 111;		// com/orange/tim/RequestTokenRW.getTokens(S[BS)S
					putfield_s 3;		// short com/orange/tim/Tim.found_tokenKeyData_length
					goto L65;
				L64:	sspush 27267;
					invokestatic 104;		// javacard/framework/ISOException.throwIt(S)V
				L65:	getfield_s_this 3;		// short com/orange/tim/Tim.found_tokenKeyData_length
					ifle L68;
				L66:	aload_0;
					getfield_a_this 52;		// reference com/orange/tim/Tim.tokenKeyData
					sconst_0;
					getfield_s_this 3;		// short com/orange/tim/Tim.found_tokenKeyData_length
					aload_2;
					aload_1;
					invokespecial 108;		// com/orange/tim/Tim.sendData([BSS[BLjavacard/framework/APDU;)S
					sstore 4;
				L67:	goto_w L122;
				L68:	sspush 27267;
					invokestatic 104;		// javacard/framework/ISOException.throwIt(S)V
					goto_w L122;
				L69:	goto_w L122;
				L70:	goto_w L122;
				L71:	aload_2;
					sconst_0;
					getfield_a_this 53;		// reference com/orange/tim/Tim.request_token_key_data
					invokevirtual 112;		// com/orange/tim/RequestTokenRW.getFreeSpace()S
					invokestatic 89;		// javacard/framework/Util.setShort([BSS)S
					pop;
					aload_1;
					invokevirtual 113;		// javacard/framework/APDU.setOutgoing()S
					pop;
					aload_1;
					sconst_2;
					invokevirtual 114;		// javacard/framework/APDU.setOutgoingLength(S)V
					aload_1;
					aload_2;
					sconst_0;
					sconst_2;
					invokevirtual 115;		// javacard/framework/APDU.sendBytesLong([BSS)V
					goto_w L122;
				L72:	aload_0;
					getfield_a_this 46;		// reference com/orange/tim/Tim.pubKey
					sconst_0;
					getfield_s_this 9;		// short com/orange/tim/Tim.pubKeyLen
					aload_2;
					aload_1;
					invokespecial 108;		// com/orange/tim/Tim.sendData([BSS[BLjavacard/framework/APDU;)S
					sstore 4;
					goto_w L122;
				L73:	aload_2;
					sconst_3;
					baload;
					ifne L75;
				L74:	aload_0;
					invokevirtual 116;		// com/orange/tim/Tim.computeTimTokenSignature()V
				L75:	getfield_s_this 12;		// short com/orange/tim/Tim.timTokenSignLen
					ifle L78;
				L76:	aload_0;
					getfield_a_this 49;		// reference com/orange/tim/Tim.timTokenSignature
					sconst_0;
					getfield_s_this 12;		// short com/orange/tim/Tim.timTokenSignLen
					aload_2;
					aload_1;
					invokespecial 108;		// com/orange/tim/Tim.sendData([BSS[BLjavacard/framework/APDU;)S
					sstore 4;
				L77:	goto_w L122;
				L78:	sspush 27012;
					invokestatic 104;		// javacard/framework/ISOException.throwIt(S)V
					goto_w L122;
				L79:	aload_0;
					getfield_a_this 53;		// reference com/orange/tim/Tim.request_token_key_data
					getfield_a 0;		// reference com/orange/tim/RequestTokenRW.tr_buffer
					sconst_0;
					getfield_a_this 53;		// reference com/orange/tim/Tim.request_token_key_data
					getfield_a 0;		// reference com/orange/tim/RequestTokenRW.tr_buffer
					arraylength;
					aload_2;
					aload_1;
					invokespecial 108;		// com/orange/tim/Tim.sendData([BSS[BLjavacard/framework/APDU;)S
					sstore 4;
					goto_w L122;
				L80:	aload_2;
					sconst_3;
					baload;
					ifne L84;
				L81:	aload_0;
					sconst_0;
					putfield_s 14;		// short com/orange/tim/Tim.signedDataLength
					getfield_s_this 13;		// short com/orange/tim/Tim.dataToSignLength
					ifgt L83;
				L82:	sspush 27012;
					invokestatic 104;		// javacard/framework/ISOException.throwIt(S)V
				L83:	getfield_a_this 60;		// reference com/orange/tim/Tim.signature
					getfield_a_this 57;		// reference com/orange/tim/Tim.timPrivKey
					sconst_1;
					invokevirtual 117;		// javacard/security/Signature.init(Ljavacard/security/Key;B)V
					aload_0;
					getfield_a_this 60;		// reference com/orange/tim/Tim.signature
					getfield_a_this 50;		// reference com/orange/tim/Tim.dataToSign
					sconst_0;
					getfield_s_this 13;		// short com/orange/tim/Tim.dataToSignLength
					getfield_a_this 51;		// reference com/orange/tim/Tim.dataSigned
					sconst_0;
					invokevirtual 118;		// javacard/security/Signature.sign([BSS[BS)S
					putfield_s 14;		// short com/orange/tim/Tim.signedDataLength
				L84:	getfield_s_this 14;		// short com/orange/tim/Tim.signedDataLength
					ifle L87;
				L85:	aload_0;
					getfield_a_this 51;		// reference com/orange/tim/Tim.dataSigned
					sconst_0;
					getfield_s_this 14;		// short com/orange/tim/Tim.signedDataLength
					aload_2;
					aload_1;
					invokespecial 108;		// com/orange/tim/Tim.sendData([BSS[BLjavacard/framework/APDU;)S
					sstore 4;
				L86:	goto_w L122;
				L87:	sspush 27012;
					invokestatic 104;		// javacard/framework/ISOException.throwIt(S)V
					goto_w L122;
				L88:	aload_2;
					sconst_0;
					sconst_1;
					bastore;
					aload_1;
					invokevirtual 113;		// javacard/framework/APDU.setOutgoing()S
					pop;
					aload_1;
					sconst_1;
					invokevirtual 114;		// javacard/framework/APDU.setOutgoingLength(S)V
					aload_1;
					aload_2;
					sconst_0;
					sconst_1;
					invokevirtual 115;		// javacard/framework/APDU.sendBytesLong([BSS)V
					goto_w L122;
				L89:	sspush 27270;
					invokestatic 104;		// javacard/framework/ISOException.throwIt(S)V
					goto_w L122;
				L90:	goto_w L122;
				L91:	goto_w L122;
				L92:	aload_2;
					sconst_2;
					baload;
					slookupswitch L122 15 1 L106 2 L108 16 L93 17 L94 18 L100 33 L95 34 L96 35 L97 36 L98 37 L99 49 L101 50 L102 51 L103 52 L104 53 L105;
				L93:	aload_0;
					invokevirtual 119;		// com/orange/tim/Tim.makeRO()V
					goto_w L122;
				L94:	aload_0;
					invokevirtual 120;		// com/orange/tim/Tim.signRO()V
					goto_w L122;
				L95:	aload_0;
					invokevirtual 121;		// com/orange/tim/Tim.signRO1()V
					goto_w L122;
				L96:	aload_0;
					invokevirtual 122;		// com/orange/tim/Tim.signRO2()V
					goto_w L122;
				L97:	aload_0;
					invokevirtual 123;		// com/orange/tim/Tim.signRO3()V
					goto_w L122;
				L98:	aload_0;
					invokevirtual 124;		// com/orange/tim/Tim.signRO4()V
					goto_w L122;
				L99:	aload_0;
					invokevirtual 125;		// com/orange/tim/Tim.signRO5()V
					goto_w L122;
				L100:	aload_0;
					invokevirtual 126;		// com/orange/tim/Tim.encryptRO()V
					goto_w L122;
				L101:	aload_0;
					invokevirtual 127;		// com/orange/tim/Tim.encryptRO1()V
					goto_w L122;
				L102:	aload_0;
					invokevirtual 128;		// com/orange/tim/Tim.encryptRO2()V
					goto_w L122;
				L103:	aload_0;
					invokevirtual 129;		// com/orange/tim/Tim.encryptRO3()V
					goto_w L122;
				L104:	aload_0;
					invokevirtual 130;		// com/orange/tim/Tim.encryptRO4()V
					goto_w L122;
				L105:	aload_0;
					invokevirtual 131;		// com/orange/tim/Tim.encryptRO5()V
					goto_w L122;
				L106:	aload_0;
					invokevirtual 119;		// com/orange/tim/Tim.makeRO()V
					aload_0;
					invokevirtual 120;		// com/orange/tim/Tim.signRO()V
					aload_0;
					invokevirtual 126;		// com/orange/tim/Tim.encryptRO()V
					getfield_s_this 8;		// short com/orange/tim/Tim.jweDataLength
					ifne_w L122;
				L107:	sspush 27267;
					invokestatic 104;		// javacard/framework/ISOException.throwIt(S)V
					goto_w L122;
				L108:	aload_2;
					sconst_3;
					baload;
					ifne_w L121;
				L109:	getfield_s_this 3;		// short com/orange/tim/Tim.found_tokenKeyData_length
					ifle_w L120;
				L110:	aload_0;
					sconst_0;
					putfield_s 9;		// short com/orange/tim/Tim.pubKeyLen
					aload_0;
					sconst_0;
					putfield_s 10;		// short com/orange/tim/Tim.privKeyLen
					getfield_a_this 63;		// reference com/orange/tim/Tim.keyPair
					ifnull L116;
				L111:	getfield_a_this 63;		// reference com/orange/tim/Tim.keyPair
					invokevirtual 132;		// javacard/security/KeyPair.genKeyPair()V
					getfield_a_this 63;		// reference com/orange/tim/Tim.keyPair
					invokevirtual 133;		// javacard/security/KeyPair.getPublic()Ljavacard/security/PublicKey;
					checkcast 0 77;		// T_CLASSORINTERFACE javacard/security/RSAPublicKey
					astore 4;
				L112:	getfield_a_this 63;		// reference com/orange/tim/Tim.keyPair
					invokevirtual 134;		// javacard/security/KeyPair.getPrivate()Ljavacard/security/PrivateKey;
					checkcast 0 72;		// T_CLASSORINTERFACE javacard/security/RSAPrivateKey
					astore 5;
				L113:	aload_0;
					aload 4;
					getfield_a_this 46;		// reference com/orange/tim/Tim.pubKey
					sconst_0;
					invokeinterface 3 77 5;		// javacard/security/RSAPublicKey
					putfield_s 9;		// short com/orange/tim/Tim.pubKeyLen
					aload_0;
					aload 5;
					getfield_a_this 47;		// reference com/orange/tim/Tim.privKey
					sconst_0;
					invokeinterface 3 72 4;		// javacard/security/RSAPrivateKey
					putfield_s 10;		// short com/orange/tim/Tim.privKeyLen
				L114:	goto L116;
				L115:	astore 4;
				L116:	getfield_s_this 9;		// short com/orange/tim/Tim.pubKeyLen
					ifeq L118;
				L117:	getfield_s_this 10;		// short com/orange/tim/Tim.privKeyLen
					ifne L119;
				L118:	aload_0;
					getstatic_a 135;		// reference com/orange/tim/Tim.defaultTimAppKey_Modulus
					arraylength;
					putfield_s 9;		// short com/orange/tim/Tim.pubKeyLen
					getstatic_a 135;		// reference com/orange/tim/Tim.defaultTimAppKey_Modulus
					sconst_0;
					getfield_a_this 46;		// reference com/orange/tim/Tim.pubKey
					sconst_0;
					getfield_s_this 9;		// short com/orange/tim/Tim.pubKeyLen
					invokestatic 69;		// javacard/framework/Util.arrayCopy([BS[BSS)S
					pop;
					aload_0;
					getstatic_a 136;		// reference com/orange/tim/Tim.defaultTimAppKey_privateExponent
					arraylength;
					putfield_s 10;		// short com/orange/tim/Tim.privKeyLen
					getstatic_a 136;		// reference com/orange/tim/Tim.defaultTimAppKey_privateExponent
					sconst_0;
					getfield_a_this 47;		// reference com/orange/tim/Tim.privKey
					sconst_0;
					getfield_s_this 10;		// short com/orange/tim/Tim.privKeyLen
					invokestatic 69;		// javacard/framework/Util.arrayCopy([BS[BSS)S
					pop;
				L119:	aload_0;
					getfield_a_this 46;		// reference com/orange/tim/Tim.pubKey
					getfield_s_this 9;		// short com/orange/tim/Tim.pubKeyLen
					getfield_a_this 47;		// reference com/orange/tim/Tim.privKey
					getfield_s_this 10;		// short com/orange/tim/Tim.privKeyLen
					invokevirtual 102;		// com/orange/tim/Tim.updateTokensAndKeys([BS[BS)Z
					pop;
					goto L122;
				L120:	sspush 27267;
					invokestatic 104;		// javacard/framework/ISOException.throwIt(S)V
					goto L122;
				L121:	sspush 27270;
					invokestatic 104;		// javacard/framework/ISOException.throwIt(S)V
				L122:	return;
			.exceptionTable {
				// start_block end_block handler_block catch_type_index
				L111 L114 L115 81;
			}
		}

		.method private setTime([BSS)V {
			.stack 5;
			.locals 0;

				L0:	aload_1;
					sload_2;
					getfield_a_this 33;		// reference com/orange/tim/Tim.currentTime
					sconst_0;
					sload_3;
					invokestatic 69;		// javacard/framework/Util.arrayCopy([BS[BSS)S
					pop;
					aload_0;
					sconst_1;
					putfield_b 32;		// boolean com/orange/tim/Tim.timeSet
					return;
		}

		.method private receiveData([BS[B)S {
			.stack 5;
			.locals 0;

				L0:	aload_1;
					sconst_3;
					baload;
					ifne L4;
				L1:	aload_0;
					aload_1;
					sconst_2;
					baload;
					putfield_b 66;		// byte com/orange/tim/Tim.currentINS
					aload_0;
					aload_1;
					sconst_3;
					baload;
					putfield_b 38;		// byte com/orange/tim/Tim.seq
					aload_0;
					sconst_0;
					putfield_s 36;		// short com/orange/tim/Tim.received_data_length
					aload_0;
					aload_1;
					sconst_5;
					invokestatic 91;		// javacard/framework/Util.getShort([BS)S
					putfield_s 35;		// short com/orange/tim/Tim.incomming
					getfield_s_this 35;		// short com/orange/tim/Tim.incomming
					aload_3;
					arraylength;
					if_scmple L3;
				L2:	sspush 27268;
					invokestatic 104;		// javacard/framework/ISOException.throwIt(S)V
				L3:	aload_0;
					dup;
					getfield_s 36;		// short com/orange/tim/Tim.received_data_length
					sload_2;
					sconst_2;
					ssub;
					sadd;
					putfield_s 36;		// short com/orange/tim/Tim.received_data_length
					aload_1;
					bspush 7;
					aload_3;
					sconst_0;
					getfield_s_this 36;		// short com/orange/tim/Tim.received_data_length
					invokestatic 69;		// javacard/framework/Util.arrayCopy([BS[BSS)S
					pop;
					goto L7;
				L4:	aload_1;
					sconst_3;
					baload;
					getfield_b_this 38;		// byte com/orange/tim/Tim.seq
					sconst_1;
					sadd;
					if_scmpne L6;
				L5:	aload_1;
					sconst_5;
					aload_3;
					getfield_s_this 36;		// short com/orange/tim/Tim.received_data_length
					sload_2;
					invokestatic 69;		// javacard/framework/Util.arrayCopy([BS[BSS)S
					pop;
					aload_0;
					dup;
					getfield_s 36;		// short com/orange/tim/Tim.received_data_length
					sload_2;
					sadd;
					putfield_s 36;		// short com/orange/tim/Tim.received_data_length
					aload_0;
					dup;
					getfield_b 38;		// byte com/orange/tim/Tim.seq
					sconst_1;
					sadd;
					s2b;
					putfield_b 38;		// byte com/orange/tim/Tim.seq
					goto L7;
				L6:	sspush 27392;
					invokestatic 104;		// javacard/framework/ISOException.throwIt(S)V
				L7:	getfield_s_this 35;		// short com/orange/tim/Tim.incomming
					getfield_s_this 36;		// short com/orange/tim/Tim.received_data_length
					ssub;
					ifle L9;
				L8:	sconst_m1;
					sreturn;
				L9:	getfield_s_this 35;		// short com/orange/tim/Tim.incomming
					sreturn;
		}

		.method private sendData([BSS[BLjavacard/framework/APDU;)S {
			.stack 5;
			.locals 0;

			.descriptor	Ljavacard/framework/APDU;	1.10;

				L0:	aload 4;
					sconst_3;
					baload;
					ifne_w L6;
				L1:	aload_0;
					aload 4;
					sconst_2;
					baload;
					putfield_b 66;		// byte com/orange/tim/Tim.currentINS
					aload_0;
					aload 4;
					sconst_3;
					baload;
					putfield_b 38;		// byte com/orange/tim/Tim.seq
					getfield_b_this 38;		// byte com/orange/tim/Tim.seq
					ifge L3;
				L2:	sspush 27392;
					invokestatic 104;		// javacard/framework/ISOException.throwIt(S)V
				L3:	aload_0;
					sconst_0;
					putfield_s 37;		// short com/orange/tim/Tim.sent
					sload_3;
					sconst_2;
					sadd;
					bspush 120;
					if_scmpgt L5;
				L4:	aload 4;
					sconst_0;
					sload_3;
					invokestatic 89;		// javacard/framework/Util.setShort([BSS)S
					pop;
					aload_1;
					sload_2;
					aload 4;
					sconst_2;
					sload_3;
					invokestatic 69;		// javacard/framework/Util.arrayCopy([BS[BSS)S
					pop;
					aload 5;
					invokevirtual 113;		// javacard/framework/APDU.setOutgoing()S
					pop;
					aload 5;
					sload_3;
					sconst_2;
					sadd;
					invokevirtual 114;		// javacard/framework/APDU.setOutgoingLength(S)V
					aload 5;
					aload 4;
					sconst_0;
					sload_3;
					sconst_2;
					sadd;
					invokevirtual 115;		// javacard/framework/APDU.sendBytesLong([BSS)V
					aload_0;
					dup;
					getfield_s 37;		// short com/orange/tim/Tim.sent
					sload_3;
					sadd;
					putfield_s 37;		// short com/orange/tim/Tim.sent
					goto_w L12;
				L5:	aload 4;
					sconst_0;
					sload_3;
					invokestatic 89;		// javacard/framework/Util.setShort([BSS)S
					pop;
					aload_1;
					sload_2;
					aload 4;
					sconst_2;
					bspush 118;
					invokestatic 69;		// javacard/framework/Util.arrayCopy([BS[BSS)S
					pop;
					aload 5;
					invokevirtual 113;		// javacard/framework/APDU.setOutgoing()S
					pop;
					aload 5;
					bspush 120;
					invokevirtual 114;		// javacard/framework/APDU.setOutgoingLength(S)V
					aload 5;
					aload 4;
					sconst_0;
					bspush 120;
					invokevirtual 115;		// javacard/framework/APDU.sendBytesLong([BSS)V
					aload_0;
					dup;
					getfield_s 37;		// short com/orange/tim/Tim.sent
					bspush 118;
					sadd;
					putfield_s 37;		// short com/orange/tim/Tim.sent
					goto L12;
				L6:	aload 4;
					sconst_3;
					baload;
					getfield_b_this 38;		// byte com/orange/tim/Tim.seq
					sconst_1;
					sadd;
					if_scmpne L11;
				L7:	sload_3;
					getfield_s_this 37;		// short com/orange/tim/Tim.sent
					ssub;
					bspush 120;
					if_scmpgt L9;
				L8:	aload 5;
					invokevirtual 113;		// javacard/framework/APDU.setOutgoing()S
					pop;
					aload 5;
					sload_3;
					getfield_s_this 37;		// short com/orange/tim/Tim.sent
					ssub;
					invokevirtual 114;		// javacard/framework/APDU.setOutgoingLength(S)V
					aload 5;
					aload_1;
					getfield_s_this 37;		// short com/orange/tim/Tim.sent
					sload_3;
					getfield_s_this 37;		// short com/orange/tim/Tim.sent
					ssub;
					invokevirtual 115;		// javacard/framework/APDU.sendBytesLong([BSS)V
					aload_0;
					dup;
					getfield_s 37;		// short com/orange/tim/Tim.sent
					sload_3;
					getfield_s_this 37;		// short com/orange/tim/Tim.sent
					ssub;
					sadd;
					putfield_s 37;		// short com/orange/tim/Tim.sent
					goto L10;
				L9:	aload 5;
					invokevirtual 113;		// javacard/framework/APDU.setOutgoing()S
					pop;
					aload 5;
					bspush 120;
					invokevirtual 114;		// javacard/framework/APDU.setOutgoingLength(S)V
					aload 5;
					aload_1;
					getfield_s_this 37;		// short com/orange/tim/Tim.sent
					bspush 120;
					invokevirtual 115;		// javacard/framework/APDU.sendBytesLong([BSS)V
					aload_0;
					dup;
					getfield_s 37;		// short com/orange/tim/Tim.sent
					bspush 120;
					sadd;
					putfield_s 37;		// short com/orange/tim/Tim.sent
				L10:	aload_0;
					dup;
					getfield_b 38;		// byte com/orange/tim/Tim.seq
					sconst_1;
					sadd;
					s2b;
					putfield_b 38;		// byte com/orange/tim/Tim.seq
					goto L12;
				L11:	sspush 27392;
					invokestatic 104;		// javacard/framework/ISOException.throwIt(S)V
				L12:	sload_3;
					getfield_s_this 37;		// short com/orange/tim/Tim.sent
					ssub;
					ifle L14;
				L13:	sconst_m1;
					sreturn;
				L14:	getfield_s_this 37;		// short com/orange/tim/Tim.sent
					sreturn;
		}

		.method public encode64URL([BSS[B)S 8 {
			.stack 4;
			.locals 11;

				L0:	sload_3;
					sconst_4;
					smul;
					sconst_2;
					sadd;
					sconst_3;
					sdiv;
					sstore 5;
				L1:	sload_2;
					sstore 6;
				L2:	sload_2;
					sload_3;
					sadd;
					sstore 7;
				L3:	sconst_0;
					sstore 8;
				L4:	goto_w L22;
				L5:	aload_1;
					sload 6;
					baload;
					sspush 255;
					sand;
					sstore 9;
				L6:	sinc 6 1;
					sload 6;
					sload 7;
					if_scmpge L9;
				L7:	aload_1;
					sload 6;
					baload;
					sspush 255;
					sand;
					sstore 10;
				L8:	sinc 6 1;
					goto L10;
				L9:	sconst_0;
					sstore 10;
				L10:	sload 6;
					sload 7;
					if_scmpge L13;
				L11:	aload_1;
					sload 6;
					baload;
					sspush 255;
					sand;
					sstore 11;
				L12:	sinc 6 1;
					goto L14;
				L13:	sconst_0;
					sstore 11;
				L14:	sload 9;
					sconst_2;
					sushr;
					sstore 12;
				L15:	sload 9;
					sconst_3;
					sand;
					sconst_4;
					sshl;
					sload 10;
					sconst_4;
					sushr;
					sor;
					sstore 13;
				L16:	sload 10;
					bspush 15;
					sand;
					sconst_2;
					sshl;
					sload 11;
					bspush 6;
					sushr;
					sor;
					sstore 14;
				L17:	sload 11;
					bspush 63;
					sand;
					sstore 15;
				L18:	aload 4;
					sload 8;
					getstatic_a 138;		// reference com/orange/tim/Tim.map64
					sload 12;
					baload;
					bastore;
					sinc 8 1;
					aload 4;
					sload 8;
					getstatic_a 138;		// reference com/orange/tim/Tim.map64
					sload 13;
					baload;
					bastore;
					sinc 8 1;
					sload 8;
					sload 5;
					if_scmpge L20;
				L19:	aload 4;
					sload 8;
					getstatic_a 138;		// reference com/orange/tim/Tim.map64
					sload 14;
					baload;
					bastore;
					sinc 8 1;
				L20:	sload 8;
					sload 5;
					if_scmpge L22;
				L21:	aload 4;
					sload 8;
					getstatic_a 138;		// reference com/orange/tim/Tim.map64
					sload 15;
					baload;
					bastore;
					sinc 8 1;
				L22:	sload 6;
					sload 7;
					if_scmplt_w L5;
				L23:	sload 5;
					sreturn;
		}

		.method private decode64URL([BSS)S {
			.stack 6;
			.locals 5;

				L0:	sload_2;
					sload_3;
					sadd;
					sstore 4;
				L1:	sconst_0;
					sstore 5;
				L2:	sconst_0;
					sstore 6;
				L3:	sconst_0;
					sstore 7;
				L4:	sload_2;
					sstore 8;
				L5:	goto_w L18;
				L6:	getstatic_a 139;		// reference com/orange/tim/Tim._URL_SAFE_DECODABET
					aload_1;
					sload 8;
					baload;
					sspush 255;
					sand;
					baload;
					sstore 7;
					sload 7;
					bspush -5;
					if_scmplt_w L16;
				L7:	sload 7;
					sconst_m1;
					if_scmplt_w L17;
				L8:	getfield_a_this 15;		// reference com/orange/tim/Tim.tempBuf64
					sload 6;
					dup;
					sconst_1;
					sadd;
					sstore 6;
					aload_1;
					sload 8;
					baload;
					bastore;
					sload 6;
					sconst_3;
					if_scmple_w L17;
				L9:	getfield_a_this 15;		// reference com/orange/tim/Tim.tempBuf64
					sconst_2;
					baload;
					bspush 61;
					if_scmpne L11;
				L10:	aload_1;
					sload 5;
					getstatic_a 139;		// reference com/orange/tim/Tim._URL_SAFE_DECODABET
					getfield_a_this 15;		// reference com/orange/tim/Tim.tempBuf64
					sconst_0;
					baload;
					baload;
					sspush 255;
					sand;
					sconst_2;
					sshl;
					getstatic_a 139;		// reference com/orange/tim/Tim._URL_SAFE_DECODABET
					getfield_a_this 15;		// reference com/orange/tim/Tim.tempBuf64
					sconst_1;
					baload;
					baload;
					sspush 255;
					sand;
					sconst_4;
					sshr;
					sconst_3;
					sand;
					sor;
					s2b;
					bastore;
					sinc 5 1;
					goto_w L14;
				L11:	getfield_a_this 15;		// reference com/orange/tim/Tim.tempBuf64
					sconst_3;
					baload;
					bspush 61;
					if_scmpne L13;
				L12:	aload_1;
					sload 5;
					getstatic_a 139;		// reference com/orange/tim/Tim._URL_SAFE_DECODABET
					getfield_a_this 15;		// reference com/orange/tim/Tim.tempBuf64
					sconst_0;
					baload;
					baload;
					sspush 255;
					sand;
					sconst_2;
					sshl;
					getstatic_a 139;		// reference com/orange/tim/Tim._URL_SAFE_DECODABET
					getfield_a_this 15;		// reference com/orange/tim/Tim.tempBuf64
					sconst_1;
					baload;
					baload;
					sspush 255;
					sand;
					sconst_4;
					sshr;
					sconst_3;
					sand;
					sor;
					s2b;
					bastore;
					aload_1;
					sload 5;
					sconst_1;
					sadd;
					getstatic_a 139;		// reference com/orange/tim/Tim._URL_SAFE_DECODABET
					getfield_a_this 15;		// reference com/orange/tim/Tim.tempBuf64
					sconst_1;
					baload;
					baload;
					sspush 255;
					sand;
					sconst_4;
					sshl;
					getstatic_a 139;		// reference com/orange/tim/Tim._URL_SAFE_DECODABET
					getfield_a_this 15;		// reference com/orange/tim/Tim.tempBuf64
					sconst_2;
					baload;
					baload;
					sspush 255;
					sand;
					sconst_2;
					sshr;
					sor;
					s2b;
					bastore;
					sinc 5 2;
					goto L14;
				L13:	aload_1;
					sload 5;
					getstatic_a 139;		// reference com/orange/tim/Tim._URL_SAFE_DECODABET
					getfield_a_this 15;		// reference com/orange/tim/Tim.tempBuf64
					sconst_0;
					baload;
					baload;
					sspush 255;
					sand;
					sconst_2;
					sshl;
					getstatic_a 139;		// reference com/orange/tim/Tim._URL_SAFE_DECODABET
					getfield_a_this 15;		// reference com/orange/tim/Tim.tempBuf64
					sconst_1;
					baload;
					baload;
					sspush 255;
					sand;
					sconst_4;
					sshr;
					sconst_3;
					sand;
					sor;
					s2b;
					bastore;
					aload_1;
					sload 5;
					sconst_1;
					sadd;
					getstatic_a 139;		// reference com/orange/tim/Tim._URL_SAFE_DECODABET
					getfield_a_this 15;		// reference com/orange/tim/Tim.tempBuf64
					sconst_1;
					baload;
					baload;
					sspush 255;
					sand;
					sconst_4;
					sshl;
					getstatic_a 139;		// reference com/orange/tim/Tim._URL_SAFE_DECODABET
					getfield_a_this 15;		// reference com/orange/tim/Tim.tempBuf64
					sconst_2;
					baload;
					baload;
					sspush 255;
					sand;
					sconst_2;
					sshr;
					sor;
					s2b;
					bastore;
					aload_1;
					sload 5;
					sconst_2;
					sadd;
					getstatic_a 139;		// reference com/orange/tim/Tim._URL_SAFE_DECODABET
					getfield_a_this 15;		// reference com/orange/tim/Tim.tempBuf64
					sconst_2;
					baload;
					baload;
					sspush 255;
					sand;
					bspush 6;
					sshl;
					getstatic_a 139;		// reference com/orange/tim/Tim._URL_SAFE_DECODABET
					getfield_a_this 15;		// reference com/orange/tim/Tim.tempBuf64
					sconst_3;
					baload;
					baload;
					sspush 255;
					sand;
					sor;
					s2b;
					bastore;
					sinc 5 3;
				L14:	sconst_0;
					sstore 6;
					aload_1;
					sload 8;
					baload;
					bspush 61;
					if_scmpne L17;
				L15:	goto L19;
				L16:	sspush 27264;
					invokestatic 104;		// javacard/framework/ISOException.throwIt(S)V
				L17:	sinc 8 1;
				L18:	sload 8;
					sload 4;
					if_scmplt_w L6;
				L19:	getfield_a_this 15;		// reference com/orange/tim/Tim.tempBuf64
					sconst_0;
					sconst_0;
					bastore;
					getfield_a_this 15;		// reference com/orange/tim/Tim.tempBuf64
					sconst_1;
					sconst_0;
					bastore;
					getfield_a_this 15;		// reference com/orange/tim/Tim.tempBuf64
					sconst_2;
					sconst_0;
					bastore;
					getfield_a_this 15;		// reference com/orange/tim/Tim.tempBuf64
					sconst_3;
					sconst_0;
					bastore;
					sload 5;
					sreturn;
		}

		.method  makeRO()V 128 {
			.stack 6;
			.locals 3;

				L0:	getfield_a_this 40;		// reference com/orange/tim/Tim.requestObjectData
					sconst_0;
					bspush 123;
					bastore;
					sconst_1;
					sstore_1;
				L1:	getstatic_a 140;		// reference com/orange/tim/Tim.data_client_id
					sconst_0;
					getfield_a_this 40;		// reference com/orange/tim/Tim.requestObjectData
					sload_1;
					getstatic_a 140;		// reference com/orange/tim/Tim.data_client_id
					arraylength;
					invokestatic 69;		// javacard/framework/Util.arrayCopy([BS[BSS)S
					sstore_1;
					getstatic_a 107;		// reference com/orange/tim/Tim.TIM_ID
					sconst_0;
					getfield_a_this 40;		// reference com/orange/tim/Tim.requestObjectData
					sload_1;
					getstatic_a 107;		// reference com/orange/tim/Tim.TIM_ID
					arraylength;
					invokestatic 69;		// javacard/framework/Util.arrayCopy([BS[BSS)S
					sstore_1;
					getstatic_a 141;		// reference com/orange/tim/Tim.json_separator
					sconst_0;
					getfield_a_this 40;		// reference com/orange/tim/Tim.requestObjectData
					sload_1;
					getstatic_a 141;		// reference com/orange/tim/Tim.json_separator
					arraylength;
					invokestatic 69;		// javacard/framework/Util.arrayCopy([BS[BSS)S
					sstore_1;
					getfield_a_this 39;		// reference com/orange/tim/Tim.requestData
					sconst_2;
					sconst_0;
					invokestatic 149;		// com/orange/tim/RequestTokenRW.skipParam([BSS)S
					sstore_2;
				L2:	getfield_a_this 39;		// reference com/orange/tim/Tim.requestData
					sload_2;
					invokestatic 91;		// javacard/framework/Util.getShort([BS)S
					sstore_3;
				L3:	sinc 2 2;
					getstatic_a 142;		// reference com/orange/tim/Tim.data_redirect_uri
					sconst_0;
					getfield_a_this 40;		// reference com/orange/tim/Tim.requestObjectData
					sload_1;
					getstatic_a 142;		// reference com/orange/tim/Tim.data_redirect_uri
					arraylength;
					invokestatic 69;		// javacard/framework/Util.arrayCopy([BS[BSS)S
					sstore_1;
					getfield_a_this 39;		// reference com/orange/tim/Tim.requestData
					sload_2;
					getfield_a_this 40;		// reference com/orange/tim/Tim.requestObjectData
					sload_1;
					sload_3;
					invokestatic 69;		// javacard/framework/Util.arrayCopy([BS[BSS)S
					sstore_1;
					getstatic_a 141;		// reference com/orange/tim/Tim.json_separator
					sconst_0;
					getfield_a_this 40;		// reference com/orange/tim/Tim.requestObjectData
					sload_1;
					getstatic_a 141;		// reference com/orange/tim/Tim.json_separator
					arraylength;
					invokestatic 69;		// javacard/framework/Util.arrayCopy([BS[BSS)S
					sstore_1;
					sload_2;
					sload_3;
					sadd;
					sstore_2;
					getfield_a_this 39;		// reference com/orange/tim/Tim.requestData
					sload_2;
					invokestatic 91;		// javacard/framework/Util.getShort([BS)S
					sstore_3;
					sinc 2 2;
					getstatic_a 143;		// reference com/orange/tim/Tim.data_scope
					sconst_0;
					getfield_a_this 40;		// reference com/orange/tim/Tim.requestObjectData
					sload_1;
					getstatic_a 143;		// reference com/orange/tim/Tim.data_scope
					arraylength;
					invokestatic 69;		// javacard/framework/Util.arrayCopy([BS[BSS)S
					sstore_1;
					getfield_a_this 39;		// reference com/orange/tim/Tim.requestData
					sload_2;
					getfield_a_this 40;		// reference com/orange/tim/Tim.requestObjectData
					sload_1;
					sload_3;
					invokestatic 69;		// javacard/framework/Util.arrayCopy([BS[BSS)S
					sstore_1;
					getstatic_a 141;		// reference com/orange/tim/Tim.json_separator
					sconst_0;
					getfield_a_this 40;		// reference com/orange/tim/Tim.requestObjectData
					sload_1;
					getstatic_a 141;		// reference com/orange/tim/Tim.json_separator
					arraylength;
					invokestatic 69;		// javacard/framework/Util.arrayCopy([BS[BSS)S
					sstore_1;
					getstatic_a 144;		// reference com/orange/tim/Tim.data_response_type
					sconst_0;
					getfield_a_this 40;		// reference com/orange/tim/Tim.requestObjectData
					sload_1;
					getstatic_a 144;		// reference com/orange/tim/Tim.data_response_type
					arraylength;
					invokestatic 69;		// javacard/framework/Util.arrayCopy([BS[BSS)S
					sstore_1;
					getstatic_a 141;		// reference com/orange/tim/Tim.json_separator
					sconst_0;
					getfield_a_this 40;		// reference com/orange/tim/Tim.requestObjectData
					sload_1;
					getstatic_a 141;		// reference com/orange/tim/Tim.json_separator
					arraylength;
					invokestatic 69;		// javacard/framework/Util.arrayCopy([BS[BSS)S
					sstore_1;
					getstatic_a 145;		// reference com/orange/tim/Tim.data_tim_params_begin
					sconst_0;
					getfield_a_this 40;		// reference com/orange/tim/Tim.requestObjectData
					sload_1;
					getstatic_a 145;		// reference com/orange/tim/Tim.data_tim_params_begin
					arraylength;
					invokestatic 69;		// javacard/framework/Util.arrayCopy([BS[BSS)S
					sstore_1;
					getfield_a_this 39;		// reference com/orange/tim/Tim.requestData
					sconst_1;
					sconst_0;
					invokestatic 149;		// com/orange/tim/RequestTokenRW.skipParam([BSS)S
					sstore_2;
					getfield_a_this 39;		// reference com/orange/tim/Tim.requestData
					sload_2;
					invokestatic 91;		// javacard/framework/Util.getShort([BS)S
					sstore_3;
					sinc 2 2;
					getfield_a_this 39;		// reference com/orange/tim/Tim.requestData
					sload_2;
					getfield_a_this 40;		// reference com/orange/tim/Tim.requestObjectData
					sload_1;
					sload_3;
					invokestatic 69;		// javacard/framework/Util.arrayCopy([BS[BSS)S
					sstore_1;
					aload_0;
					getstatic_a 146;		// reference com/orange/tim/Tim.data_tim_params_end
					sconst_0;
					getfield_a_this 40;		// reference com/orange/tim/Tim.requestObjectData
					sload_1;
					getstatic_a 146;		// reference com/orange/tim/Tim.data_tim_params_end
					arraylength;
					invokestatic 69;		// javacard/framework/Util.arrayCopy([BS[BSS)S
					putfield_s 6;		// short com/orange/tim/Tim.requestObjectLength
					getfield_a_this 40;		// reference com/orange/tim/Tim.requestObjectData
					getfield_s_this 6;		// short com/orange/tim/Tim.requestObjectLength
					bspush 125;
					bastore;
					aload_0;
					dup;
					getfield_s 6;		// short com/orange/tim/Tim.requestObjectLength
					sconst_1;
					sadd;
					putfield_s 6;		// short com/orange/tim/Tim.requestObjectLength
					return;
		}

		.method  signRO()V 129 {
			.stack 1;
			.locals 0;

				L0:	aload_0;
					invokevirtual 121;		// com/orange/tim/Tim.signRO1()V
					aload_0;
					invokevirtual 122;		// com/orange/tim/Tim.signRO2()V
					aload_0;
					invokevirtual 123;		// com/orange/tim/Tim.signRO3()V
					aload_0;
					invokevirtual 124;		// com/orange/tim/Tim.signRO4()V
					aload_0;
					invokevirtual 125;		// com/orange/tim/Tim.signRO5()V
					return;
		}

		.method  signRO1()V 130 {
			.stack 6;
			.locals 0;

				L0:	aload_0;
					aload_0;
					getfield_a_this 40;		// reference com/orange/tim/Tim.requestObjectData
					sconst_0;
					getfield_s_this 6;		// short com/orange/tim/Tim.requestObjectLength
					getfield_a_this 41;		// reference com/orange/tim/Tim.encoded64
					invokevirtual 147;		// com/orange/tim/Tim.encode64URL([BSS[B)S
					putfield_s 6;		// short com/orange/tim/Tim.requestObjectLength
					getfield_a_this 41;		// reference com/orange/tim/Tim.encoded64
					sconst_0;
					getfield_a_this 40;		// reference com/orange/tim/Tim.requestObjectData
					sconst_0;
					getfield_s_this 6;		// short com/orange/tim/Tim.requestObjectLength
					invokestatic 69;		// javacard/framework/Util.arrayCopy([BS[BSS)S
					pop;
					return;
		}

		.method  signRO2()V 131 {
			.stack 6;
			.locals 0;

				L0:	aload_0;
					getfield_a_this 18;		// reference com/orange/tim/Tim.sha1withrsaHeaderB64
					sconst_0;
					getfield_a_this 44;		// reference com/orange/tim/Tim.signedRequestObjectData
					sconst_0;
					getfield_a_this 18;		// reference com/orange/tim/Tim.sha1withrsaHeaderB64
					arraylength;
					invokestatic 69;		// javacard/framework/Util.arrayCopy([BS[BSS)S
					putfield_s 20;		// short com/orange/tim/Tim.signRO_offset
					getfield_a_this 44;		// reference com/orange/tim/Tim.signedRequestObjectData
					getfield_s_this 20;		// short com/orange/tim/Tim.signRO_offset
					bspush 46;
					bastore;
					aload_0;
					dup;
					getfield_s 20;		// short com/orange/tim/Tim.signRO_offset
					sconst_1;
					sadd;
					putfield_s 20;		// short com/orange/tim/Tim.signRO_offset
					aload_0;
					getfield_a_this 40;		// reference com/orange/tim/Tim.requestObjectData
					sconst_0;
					getfield_a_this 44;		// reference com/orange/tim/Tim.signedRequestObjectData
					getfield_s_this 20;		// short com/orange/tim/Tim.signRO_offset
					getfield_s_this 6;		// short com/orange/tim/Tim.requestObjectLength
					invokestatic 69;		// javacard/framework/Util.arrayCopy([BS[BSS)S
					putfield_s 20;		// short com/orange/tim/Tim.signRO_offset
					return;
		}

		.method  signRO3()V 132 {
			.stack 7;
			.locals 0;

				L0:	getfield_a_this 60;		// reference com/orange/tim/Tim.signature
					getfield_a_this 57;		// reference com/orange/tim/Tim.timPrivKey
					sconst_1;
					invokevirtual 117;		// javacard/security/Signature.init(Ljavacard/security/Key;B)V
					aload_0;
					getfield_a_this 60;		// reference com/orange/tim/Tim.signature
					getfield_a_this 44;		// reference com/orange/tim/Tim.signedRequestObjectData
					sconst_0;
					getfield_s_this 20;		// short com/orange/tim/Tim.signRO_offset
					getfield_a_this 43;		// reference com/orange/tim/Tim.requestObjectDataSignature
					sconst_0;
					invokevirtual 118;		// javacard/security/Signature.sign([BSS[BS)S
					putfield_s 21;		// short com/orange/tim/Tim.signature_len
					return;
		}

		.method  signRO4()V 133 {
			.stack 6;
			.locals 0;

				L0:	aload_0;
					aload_0;
					getfield_a_this 43;		// reference com/orange/tim/Tim.requestObjectDataSignature
					sconst_0;
					getfield_s_this 21;		// short com/orange/tim/Tim.signature_len
					getfield_a_this 41;		// reference com/orange/tim/Tim.encoded64
					invokevirtual 147;		// com/orange/tim/Tim.encode64URL([BSS[B)S
					putfield_s 21;		// short com/orange/tim/Tim.signature_len
					return;
		}

		.method  signRO5()V 134 {
			.stack 6;
			.locals 0;

				L0:	getfield_a_this 44;		// reference com/orange/tim/Tim.signedRequestObjectData
					getfield_s_this 20;		// short com/orange/tim/Tim.signRO_offset
					bspush 46;
					bastore;
					aload_0;
					dup;
					getfield_s 20;		// short com/orange/tim/Tim.signRO_offset
					sconst_1;
					sadd;
					putfield_s 20;		// short com/orange/tim/Tim.signRO_offset
					aload_0;
					getfield_a_this 41;		// reference com/orange/tim/Tim.encoded64
					sconst_0;
					getfield_a_this 44;		// reference com/orange/tim/Tim.signedRequestObjectData
					getfield_s_this 20;		// short com/orange/tim/Tim.signRO_offset
					getfield_s_this 21;		// short com/orange/tim/Tim.signature_len
					invokestatic 69;		// javacard/framework/Util.arrayCopy([BS[BSS)S
					putfield_s 7;		// short com/orange/tim/Tim.signedRequestObjectLength
					return;
		}

		.method  encryptRO()V 135 {
			.stack 1;
			.locals 0;

				L0:	aload_0;
					invokevirtual 127;		// com/orange/tim/Tim.encryptRO1()V
					aload_0;
					invokevirtual 128;		// com/orange/tim/Tim.encryptRO2()V
					aload_0;
					invokevirtual 129;		// com/orange/tim/Tim.encryptRO3()V
					aload_0;
					invokevirtual 130;		// com/orange/tim/Tim.encryptRO4()V
					aload_0;
					invokevirtual 131;		// com/orange/tim/Tim.encryptRO5()V
					return;
		}

		.method  encryptRO1()V 136 {
			.stack 6;
			.locals 0;

				L0:	aload_0;
					sconst_0;
					putfield_s 22;		// short com/orange/tim/Tim.encryptRO_offset
					aload_0;
					getstatic_a 148;		// reference com/orange/tim/Tim.jweHeader64
					sconst_0;
					getfield_a_this 45;		// reference com/orange/tim/Tim.jweData
					getfield_s_this 22;		// short com/orange/tim/Tim.encryptRO_offset
					getstatic_a 148;		// reference com/orange/tim/Tim.jweHeader64
					arraylength;
					invokestatic 69;		// javacard/framework/Util.arrayCopy([BS[BSS)S
					putfield_s 22;		// short com/orange/tim/Tim.encryptRO_offset
					getfield_a_this 45;		// reference com/orange/tim/Tim.jweData
					getfield_s_this 22;		// short com/orange/tim/Tim.encryptRO_offset
					bspush 46;
					bastore;
					aload_0;
					dup;
					getfield_s 22;		// short com/orange/tim/Tim.encryptRO_offset
					sconst_1;
					sadd;
					putfield_s 22;		// short com/orange/tim/Tim.encryptRO_offset
					getfield_a_this 67;		// reference com/orange/tim/Tim.secure_random
					ifnull L2;
				L1:	getfield_a_this 67;		// reference com/orange/tim/Tim.secure_random
					getfield_a_this 25;		// reference com/orange/tim/Tim.cek
					sconst_0;
					getfield_a_this 25;		// reference com/orange/tim/Tim.cek
					arraylength;
					invokevirtual 150;		// javacard/security/RandomData.generateData([BSS)V
					goto L3;
				L2:	getfield_a_this 64;		// reference com/orange/tim/Tim.pseudo_random
					getfield_a_this 25;		// reference com/orange/tim/Tim.cek
					sconst_0;
					getfield_a_this 25;		// reference com/orange/tim/Tim.cek
					arraylength;
					invokevirtual 150;		// javacard/security/RandomData.generateData([BSS)V
				L3:	return;
		}

		.method  encryptRO2()V 137 {
			.stack 7;
			.locals 1;

				L0:	aload_0;
					sconst_0;
					putfield_s 23;		// short com/orange/tim/Tim.encryptRO_length
					getfield_a_this 62;		// reference com/orange/tim/Tim.cipherRsaServer
					ifnull L2;
				L1:	aload_0;
					getfield_a_this 62;		// reference com/orange/tim/Tim.cipherRsaServer
					getfield_a_this 25;		// reference com/orange/tim/Tim.cek
					sconst_0;
					getfield_a_this 25;		// reference com/orange/tim/Tim.cek
					arraylength;
					getfield_a_this 42;		// reference com/orange/tim/Tim.encryptData
					sconst_0;
					invokevirtual 151;		// javacardx/crypto/Cipher.doFinal([BSS[BS)S
					putfield_s 23;		// short com/orange/tim/Tim.encryptRO_length
					goto L6;
				L2:	aload_0;
					getfield_a_this 54;		// reference com/orange/tim/Tim.cipherRsaTim
					getfield_a_this 25;		// reference com/orange/tim/Tim.cek
					sconst_0;
					getfield_a_this 25;		// reference com/orange/tim/Tim.cek
					arraylength;
					getfield_a_this 42;		// reference com/orange/tim/Tim.encryptData
					sconst_0;
					invokevirtual 151;		// javacardx/crypto/Cipher.doFinal([BSS[BS)S
					putfield_s 23;		// short com/orange/tim/Tim.encryptRO_length
				L3:	goto L6;
				L4:	astore_1;
				L5:	sspush 27010;
					invokestatic 104;		// javacard/framework/ISOException.throwIt(S)V
				L6:	return;
			.exceptionTable {
				// start_block end_block handler_block catch_type_index
				L0 L3 L4 81;
			}
		}

		.method  encryptRO3()V 138 {
			.stack 6;
			.locals 1;

				L0:	aload_0;
					aload_0;
					getfield_a_this 42;		// reference com/orange/tim/Tim.encryptData
					sconst_0;
					getfield_s_this 23;		// short com/orange/tim/Tim.encryptRO_length
					getfield_a_this 41;		// reference com/orange/tim/Tim.encoded64
					invokevirtual 147;		// com/orange/tim/Tim.encode64URL([BSS[B)S
					putfield_s 23;		// short com/orange/tim/Tim.encryptRO_length
					aload_0;
					getfield_a_this 41;		// reference com/orange/tim/Tim.encoded64
					sconst_0;
					getfield_a_this 45;		// reference com/orange/tim/Tim.jweData
					getfield_s_this 22;		// short com/orange/tim/Tim.encryptRO_offset
					getfield_s_this 23;		// short com/orange/tim/Tim.encryptRO_length
					invokestatic 69;		// javacard/framework/Util.arrayCopy([BS[BSS)S
					putfield_s 22;		// short com/orange/tim/Tim.encryptRO_offset
					getfield_a_this 45;		// reference com/orange/tim/Tim.jweData
					getfield_s_this 22;		// short com/orange/tim/Tim.encryptRO_offset
					bspush 46;
					bastore;
					aload_0;
					dup;
					getfield_s 22;		// short com/orange/tim/Tim.encryptRO_offset
					sconst_1;
					sadd;
					putfield_s 22;		// short com/orange/tim/Tim.encryptRO_offset
					getfield_a_this 67;		// reference com/orange/tim/Tim.secure_random
					ifnull L2;
				L1:	getfield_a_this 67;		// reference com/orange/tim/Tim.secure_random
					getfield_a_this 26;		// reference com/orange/tim/Tim.iv_key
					sconst_0;
					getfield_a_this 26;		// reference com/orange/tim/Tim.iv_key
					arraylength;
					invokevirtual 150;		// javacard/security/RandomData.generateData([BSS)V
					goto L3;
				L2:	getfield_a_this 64;		// reference com/orange/tim/Tim.pseudo_random
					getfield_a_this 26;		// reference com/orange/tim/Tim.iv_key
					sconst_0;
					getfield_a_this 26;		// reference com/orange/tim/Tim.iv_key
					arraylength;
					invokevirtual 150;		// javacard/security/RandomData.generateData([BSS)V
				L3:	aload_0;
					aload_0;
					getfield_a_this 26;		// reference com/orange/tim/Tim.iv_key
					sconst_0;
					getfield_a_this 26;		// reference com/orange/tim/Tim.iv_key
					arraylength;
					getfield_a_this 41;		// reference com/orange/tim/Tim.encoded64
					invokevirtual 147;		// com/orange/tim/Tim.encode64URL([BSS[B)S
					putfield_s 23;		// short com/orange/tim/Tim.encryptRO_length
					aload_0;
					getfield_a_this 41;		// reference com/orange/tim/Tim.encoded64
					sconst_0;
					getfield_a_this 45;		// reference com/orange/tim/Tim.jweData
					getfield_s_this 22;		// short com/orange/tim/Tim.encryptRO_offset
					getfield_s_this 23;		// short com/orange/tim/Tim.encryptRO_length
					invokestatic 69;		// javacard/framework/Util.arrayCopy([BS[BSS)S
					putfield_s 22;		// short com/orange/tim/Tim.encryptRO_offset
					getfield_a_this 45;		// reference com/orange/tim/Tim.jweData
					getfield_s_this 22;		// short com/orange/tim/Tim.encryptRO_offset
					bspush 46;
					bastore;
					aload_0;
					dup;
					getfield_s 22;		// short com/orange/tim/Tim.encryptRO_offset
					sconst_1;
					sadd;
					putfield_s 22;		// short com/orange/tim/Tim.encryptRO_offset
				L4:	goto L7;
				L5:	astore_1;
				L6:	sspush 27010;
					invokestatic 104;		// javacard/framework/ISOException.throwIt(S)V
				L7:	return;
			.exceptionTable {
				// start_block end_block handler_block catch_type_index
				L0 L4 L5 81;
			}
		}

		.method  encryptRO4()V 139 {
			.stack 7;
			.locals 3;

				L0:	getfield_s_this 7;		// short com/orange/tim/Tim.signedRequestObjectLength
					bspush 16;
					srem;
					sstore_1;
				L1:	sload_1;
					ifle L8;
				L2:	bspush 16;
					sload_1;
					ssub;
					s2b;
					sstore_2;
				L3:	sconst_0;
					sstore_3;
				L4:	goto L6;
				L5:	getfield_a_this 44;		// reference com/orange/tim/Tim.signedRequestObjectData
					getfield_s_this 7;		// short com/orange/tim/Tim.signedRequestObjectLength
					sload_3;
					sadd;
					sload_2;
					bastore;
					sload_3;
					sconst_1;
					sadd;
					s2b;
					sstore_3;
				L6:	sload_3;
					sload_2;
					if_scmplt L5;
				L7:	aload_0;
					dup;
					getfield_s 7;		// short com/orange/tim/Tim.signedRequestObjectLength
					sload_2;
					sadd;
					putfield_s 7;		// short com/orange/tim/Tim.signedRequestObjectLength
				L8:	bspush 14;
					sspush 128;
					sconst_0;
					invokestatic 71;		// javacard/security/KeyBuilder.buildKey(BSZ)Ljavacard/security/Key;
					checkcast 0 152;		// T_CLASSORINTERFACE javacard/security/AESKey
					astore_2;
				L9:	aload_2;
					getfield_a_this 25;		// reference com/orange/tim/Tim.cek
					getfield_a_this 25;		// reference com/orange/tim/Tim.cek
					arraylength;
					sconst_2;
					sdiv;
					invokeinterface 3 152 4;		// javacard/security/AESKey
					getfield_a_this 59;		// reference com/orange/tim/Tim.cipherForAESCBC
					aload_2;
					sconst_2;
					getfield_a_this 26;		// reference com/orange/tim/Tim.iv_key
					sconst_0;
					getfield_a_this 26;		// reference com/orange/tim/Tim.iv_key
					arraylength;
					invokevirtual 153;		// javacardx/crypto/Cipher.init(Ljavacard/security/Key;B[BSS)V
					aload_0;
					getfield_a_this 59;		// reference com/orange/tim/Tim.cipherForAESCBC
					getfield_a_this 44;		// reference com/orange/tim/Tim.signedRequestObjectData
					sconst_0;
					getfield_s_this 7;		// short com/orange/tim/Tim.signedRequestObjectLength
					getfield_a_this 42;		// reference com/orange/tim/Tim.encryptData
					sconst_0;
					invokevirtual 151;		// javacardx/crypto/Cipher.doFinal([BSS[BS)S
					putfield_s 24;		// short com/orange/tim/Tim.encryptRO_encrypt_length
				L10:	goto L13;
				L11:	astore_1;
				L12:	sspush 27010;
					invokestatic 104;		// javacard/framework/ISOException.throwIt(S)V
				L13:	return;
			.exceptionTable {
				// start_block end_block handler_block catch_type_index
				L0 L10 L11 81;
			}
		}

		.method  encryptRO5()V 140 {
			.stack 6;
			.locals 1;

				L0:	aload_0;
					aload_0;
					getfield_a_this 42;		// reference com/orange/tim/Tim.encryptData
					sconst_0;
					getfield_s_this 24;		// short com/orange/tim/Tim.encryptRO_encrypt_length
					getfield_a_this 41;		// reference com/orange/tim/Tim.encoded64
					invokevirtual 147;		// com/orange/tim/Tim.encode64URL([BSS[B)S
					putfield_s 23;		// short com/orange/tim/Tim.encryptRO_length
					aload_0;
					getfield_a_this 41;		// reference com/orange/tim/Tim.encoded64
					sconst_0;
					getfield_a_this 45;		// reference com/orange/tim/Tim.jweData
					getfield_s_this 22;		// short com/orange/tim/Tim.encryptRO_offset
					getfield_s_this 23;		// short com/orange/tim/Tim.encryptRO_length
					invokestatic 69;		// javacard/framework/Util.arrayCopy([BS[BSS)S
					putfield_s 22;		// short com/orange/tim/Tim.encryptRO_offset
					getfield_a_this 45;		// reference com/orange/tim/Tim.jweData
					getfield_s_this 22;		// short com/orange/tim/Tim.encryptRO_offset
					bspush 46;
					bastore;
					aload_0;
					dup;
					getfield_s 22;		// short com/orange/tim/Tim.encryptRO_offset
					sconst_1;
					sadd;
					putfield_s 22;		// short com/orange/tim/Tim.encryptRO_offset
					aload_0;
					aload_0;
					getfield_a_this 25;		// reference com/orange/tim/Tim.cek
					sconst_0;
					getfield_a_this 25;		// reference com/orange/tim/Tim.cek
					arraylength;
					sconst_2;
					sdiv;
					getfield_a_this 41;		// reference com/orange/tim/Tim.encoded64
					invokevirtual 147;		// com/orange/tim/Tim.encode64URL([BSS[B)S
					putfield_s 23;		// short com/orange/tim/Tim.encryptRO_length
					aload_0;
					getfield_a_this 41;		// reference com/orange/tim/Tim.encoded64
					sconst_0;
					getfield_a_this 45;		// reference com/orange/tim/Tim.jweData
					getfield_s_this 22;		// short com/orange/tim/Tim.encryptRO_offset
					getfield_s_this 23;		// short com/orange/tim/Tim.encryptRO_length
					invokestatic 69;		// javacard/framework/Util.arrayCopy([BS[BSS)S
					putfield_s 22;		// short com/orange/tim/Tim.encryptRO_offset
					aload_0;
					getfield_s_this 22;		// short com/orange/tim/Tim.encryptRO_offset
					putfield_s 8;		// short com/orange/tim/Tim.jweDataLength
				L1:	goto L4;
				L2:	astore_1;
				L3:	sspush 27010;
					invokestatic 104;		// javacard/framework/ISOException.throwIt(S)V
				L4:	return;
			.exceptionTable {
				// start_block end_block handler_block catch_type_index
				L0 L1 L2 81;
			}
		}

		.method  computeTimTokenSignature()V 141 {
			.stack 7;
			.locals 3;

				L0:	aload_0;
					sconst_0;
					putfield_s 12;		// short com/orange/tim/Tim.timTokenSignLen
					getfield_s_this 11;		// short com/orange/tim/Tim.timTokenLen
					sconst_1;
					if_scmpge L2;
				L1:	sspush 27012;
					invokestatic 104;		// javacard/framework/ISOException.throwIt(S)V
				L2:	getfield_a_this 53;		// reference com/orange/tim/Tim.request_token_key_data
					getfield_a_this 39;		// reference com/orange/tim/Tim.requestData
					invokevirtual 103;		// com/orange/tim/RequestTokenRW.searchRequestData([B)S
					sstore_1;
				L3:	aload_0;
					sconst_0;
					putfield_s 2;		// short com/orange/tim/Tim.found_data_length
					sload_1;
					sconst_2;
					if_scmple L5;
				L4:	aload_0;
					getfield_a_this 53;		// reference com/orange/tim/Tim.request_token_key_data
					sload_1;
					getfield_a_this 52;		// reference com/orange/tim/Tim.tokenKeyData
					sconst_0;
					invokevirtual 105;		// com/orange/tim/RequestTokenRW.getTokensAndAppKeys(S[BS)S
					putfield_s 2;		// short com/orange/tim/Tim.found_data_length
					goto L6;
				L5:	sspush 27267;
					invokestatic 104;		// javacard/framework/ISOException.throwIt(S)V
				L6:	getfield_a_this 52;		// reference com/orange/tim/Tim.tokenKeyData
					sconst_3;
					sconst_0;
					invokestatic 149;		// com/orange/tim/RequestTokenRW.skipParam([BSS)S
					sstore_1;
					getfield_a_this 52;		// reference com/orange/tim/Tim.tokenKeyData
					sload_1;
					invokestatic 91;		// javacard/framework/Util.getShort([BS)S
					sstore_2;
				L7:	sinc 1 2;
					getfield_a_this 56;		// reference com/orange/tim/Tim.appPrivKey
					getfield_a_this 52;		// reference com/orange/tim/Tim.tokenKeyData
					sload_1;
					sload_2;
					invokeinterface 4 72 7;		// javacard/security/RSAPrivateKey
					sload_1;
					sload_2;
					sadd;
					sstore_1;
					getfield_a_this 52;		// reference com/orange/tim/Tim.tokenKeyData
					sload_1;
					invokestatic 91;		// javacard/framework/Util.getShort([BS)S
					sstore_2;
					sinc 1 2;
					getfield_a_this 56;		// reference com/orange/tim/Tim.appPrivKey
					getfield_a_this 52;		// reference com/orange/tim/Tim.tokenKeyData
					sload_1;
					sload_2;
					invokeinterface 4 72 6;		// javacard/security/RSAPrivateKey
					bspush 10;
					sconst_0;
					invokestatic 82;		// javacard/security/Signature.getInstance(BZ)Ljavacard/security/Signature;
					astore_3;
				L8:	aload_3;
					getfield_a_this 56;		// reference com/orange/tim/Tim.appPrivKey
					sconst_1;
					invokevirtual 117;		// javacard/security/Signature.init(Ljavacard/security/Key;B)V
					aload_0;
					aload_3;
					getfield_a_this 48;		// reference com/orange/tim/Tim.timToken
					sconst_0;
					getfield_s_this 11;		// short com/orange/tim/Tim.timTokenLen
					getfield_a_this 49;		// reference com/orange/tim/Tim.timTokenSignature
					sconst_0;
					invokevirtual 118;		// javacard/security/Signature.sign([BSS[BS)S
					putfield_s 12;		// short com/orange/tim/Tim.timTokenSignLen
				L9:	goto_w L20;
				L10:	astore_2;
				L11:	aload_2;
					invokevirtual 155;		// javacard/framework/CardRuntimeException.getReason()S
					stableswitch L16 1 5 L15 L12 L16 L13 L14;
				L12:	aload_0;
					getfield_a_this 27;		// reference com/orange/tim/Tim.cryptoErrorK
					sconst_0;
					getfield_a_this 49;		// reference com/orange/tim/Tim.timTokenSignature
					sconst_0;
					getfield_a_this 27;		// reference com/orange/tim/Tim.cryptoErrorK
					arraylength;
					invokestatic 69;		// javacard/framework/Util.arrayCopy([BS[BSS)S
					putfield_s 12;		// short com/orange/tim/Tim.timTokenSignLen
					goto L20;
				L13:	aload_0;
					getfield_a_this 28;		// reference com/orange/tim/Tim.cryptoErrorI
					sconst_0;
					getfield_a_this 49;		// reference com/orange/tim/Tim.timTokenSignature
					sconst_0;
					getfield_a_this 28;		// reference com/orange/tim/Tim.cryptoErrorI
					arraylength;
					invokestatic 69;		// javacard/framework/Util.arrayCopy([BS[BSS)S
					putfield_s 12;		// short com/orange/tim/Tim.timTokenSignLen
					goto L20;
				L14:	aload_0;
					getfield_a_this 29;		// reference com/orange/tim/Tim.cryptoErrorU
					sconst_0;
					getfield_a_this 49;		// reference com/orange/tim/Tim.timTokenSignature
					sconst_0;
					getfield_a_this 29;		// reference com/orange/tim/Tim.cryptoErrorU
					arraylength;
					invokestatic 69;		// javacard/framework/Util.arrayCopy([BS[BSS)S
					putfield_s 12;		// short com/orange/tim/Tim.timTokenSignLen
					goto L20;
				L15:	aload_0;
					getfield_a_this 30;		// reference com/orange/tim/Tim.cryptoErrorV
					sconst_0;
					getfield_a_this 49;		// reference com/orange/tim/Tim.timTokenSignature
					sconst_0;
					getfield_a_this 30;		// reference com/orange/tim/Tim.cryptoErrorV
					arraylength;
					invokestatic 69;		// javacard/framework/Util.arrayCopy([BS[BSS)S
					putfield_s 12;		// short com/orange/tim/Tim.timTokenSignLen
					goto L20;
				L16:	aload_0;
					getfield_a_this 31;		// reference com/orange/tim/Tim.cryptoErrorD
					sconst_0;
					getfield_a_this 49;		// reference com/orange/tim/Tim.timTokenSignature
					sconst_0;
					getfield_a_this 31;		// reference com/orange/tim/Tim.cryptoErrorD
					arraylength;
					invokestatic 69;		// javacard/framework/Util.arrayCopy([BS[BSS)S
					putfield_s 12;		// short com/orange/tim/Tim.timTokenSignLen
				L17:	goto L20;
				L18:	astore_2;
				L19:	sspush 28416;
					invokestatic 104;		// javacard/framework/ISOException.throwIt(S)V
				L20:	return;
			.exceptionTable {
				// start_block end_block handler_block catch_type_index
				L6 L9 L10 154;
				L6 L9 L18 81;
			}
		}

		.method  updateTokensAndKeys([BS[BS)Z 142 {
			.stack 5;
			.locals 1;

				L0:	getfield_s_this 4;		// short com/orange/tim/Tim.tokenKeyDataLength
					ifgt L2;
				L1:	sspush 27267;
					invokestatic 104;		// javacard/framework/ISOException.throwIt(S)V
				L2:	getfield_a_this 52;		// reference com/orange/tim/Tim.tokenKeyData
					sconst_3;
					sconst_0;
					invokestatic 149;		// com/orange/tim/RequestTokenRW.skipParam([BSS)S
					sstore 5;
				L3:	getfield_a_this 52;		// reference com/orange/tim/Tim.tokenKeyData
					sload 5;
					sload_2;
					invokestatic 89;		// javacard/framework/Util.setShort([BSS)S
					sstore 5;
					aload_1;
					sconst_0;
					getfield_a_this 52;		// reference com/orange/tim/Tim.tokenKeyData
					sload 5;
					sload_2;
					invokestatic 69;		// javacard/framework/Util.arrayCopy([BS[BSS)S
					sstore 5;
					aload_0;
					sload 5;
					putfield_s 3;		// short com/orange/tim/Tim.found_tokenKeyData_length
					getfield_a_this 52;		// reference com/orange/tim/Tim.tokenKeyData
					sload 5;
					sload 4;
					invokestatic 89;		// javacard/framework/Util.setShort([BSS)S
					sstore 5;
					aload_3;
					sconst_0;
					getfield_a_this 52;		// reference com/orange/tim/Tim.tokenKeyData
					sload 5;
					sload 4;
					invokestatic 69;		// javacard/framework/Util.arrayCopy([BS[BSS)S
					sstore 5;
					getfield_a_this 53;		// reference com/orange/tim/Tim.request_token_key_data
					getfield_a_this 39;		// reference com/orange/tim/Tim.requestData
					getfield_a_this 52;		// reference com/orange/tim/Tim.tokenKeyData
					invokevirtual 156;		// com/orange/tim/RequestTokenRW.setRequestToken([B[B)Z
					ifne L5;
				L4:	sspush 27268;
					invokestatic 104;		// javacard/framework/ISOException.throwIt(S)V
				L5:	aload_0;
					sconst_0;
					putfield_s 3;		// short com/orange/tim/Tim.found_tokenKeyData_length
					aload_0;
					sconst_0;
					putfield_s 4;		// short com/orange/tim/Tim.tokenKeyDataLength
					sconst_1;
					sreturn;
		}

	}

}
